{"words":[{"word":"rover","count":24},{"word":"jinzhou","count":23},{"word":"time","count":19},{"word":"really","count":18},{"word":"panhua","count":17},{"word":"baizhi","count":16},{"word":"auntie","count":16},{"word":"oh","count":15},{"word":"yeah","count":12},{"word":"yangyang","count":12},{"word":"find","count":11},{"word":"any","count":11},{"word":"playername","count":11},{"word":"help","count":10},{"word":"little","count":10},{"word":"tacet","count":10},{"word":"always","count":9},{"word":"city","count":9},{"word":"hey","count":9},{"word":"name","count":9},{"word":"cool","count":9},{"word":"thing","count":8},{"word":"since","count":8},{"word":"male","count":8},{"word":"female","count":8},{"word":"something","count":8},{"word":"into","count":8},{"word":"check","count":8},{"word":"color","count":8},{"word":"every","count":8},{"word":"anyway","count":7},{"word":"anything","count":7},{"word":"coming","count":7},{"word":"seriously","count":7},{"word":"give","count":7},{"word":"around","count":7},{"word":"please","count":7},{"word":"call","count":7},{"word":"seems","count":7},{"word":"hmm","count":7},{"word":"uncle","count":7},{"word":"huh","count":6},{"word":"ugh","count":6},{"word":"i'll","count":6},{"word":"maybe","count":6},{"word":"trying","count":6},{"word":"real","count":6},{"word":"grandma","count":6},{"word":"wait","count":6},{"word":"remember","count":6},{"word":"said","count":6},{"word":"gotta","count":6},{"word":"figure","count":6},{"word":"echo","count":6},{"word":"days","count":6},{"word":"long","count":6},{"word":"wanna","count":6},{"word":"soup","count":6},{"word":"spoon","count":6},{"word":"first","count":5},{"word":"lot","count":5},{"word":"saw","count":5},{"word":"people","count":5},{"word":"going","count":5},{"word":"knew","count":5},{"word":"thanks","count":5},{"word":"keep","count":5},{"word":"already","count":5},{"word":"least","count":5},{"word":"sounds","count":5},{"word":"true","count":5},{"word":"gonna","count":5},{"word":"knows","count":5},{"word":"show","count":5},{"word":"made","count":5},{"word":"never","count":5},{"word":"place","count":5},{"word":"someone","count":5},{"word":"work","count":5},{"word":"super","count":5},{"word":"business","count":5},{"word":"person","count":5},{"word":"meet","count":5},{"word":"alright","count":5},{"word":"sure","count":5},{"word":"ingredients","count":5},{"word":"abby","count":5},{"word":"case","count":4},{"word":"ring","count":4},{"word":"spot","count":4},{"word":"move","count":4},{"word":"thought","count":4},{"word":"stop","count":4},{"word":"without","count":4},{"word":"patroller","count":4},{"word":"hear","count":4},{"word":"used","count":4},{"word":"special","count":4},{"word":"ask","count":4},{"word":"chixia","count":4},{"word":"wow","count":4},{"word":"stuff","count":4},{"word":"flower","count":4},{"word":"hands","count":4},{"word":"bet","count":4},{"word":"worries","count":4},{"word":"exactly","count":4},{"word":"love","count":4},{"word":"yep","count":4},{"word":"echoes","count":4},{"word":"awesome","count":4},{"word":"ano","count":4},{"word":"highlight","count":4},{"word":"big","count":4},{"word":"last","count":4},{"word":"huanglong","count":4},{"word":"discord","count":4},{"word":"taste","count":4},{"word":"folks","count":4},{"word":"food","count":4},{"word":"many","count":4},{"word":"okay","count":4},{"word":"festival","count":4},{"word":"everyone","count":4},{"word":"meal","count":4},{"word":"speedster","count":4},{"word":"culinary","count":4},{"word":"street","count":4},{"word":"essence","count":4},{"word":"whip","count":4},{"word":"wei","count":4},{"word":"weapon","count":4},{"word":"use","count":3},{"word":"missing","count":3},{"word":"ever","count":3},{"word":"resonators","count":3},{"word":"thank","count":3},{"word":"saying","count":3},{"word":"guess","count":3},{"word":"either","count":3},{"word":"bad","count":3},{"word":"catch","count":3},{"word":"happened","count":3},{"word":"general","count":3},{"word":"jiyan","count":3},{"word":"sentinel","count":3},{"word":"magistrate","count":3},{"word":"day","count":3},{"word":"'em","count":3},{"word":"running","count":3},{"word":"black","count":3},{"word":"i've","count":3},{"word":"seen","count":3},{"word":"lin","count":3},{"word":"hehe","count":3},{"word":"earlier","count":3},{"word":"'s","count":3},{"word":"kind","count":3},{"word":"speaking","count":3},{"word":"good","count":3},{"word":"worry","count":3},{"word":"strong","count":3},{"word":"looking","count":3},{"word":"license","count":3},{"word":"believe","count":3},{"word":"station","count":3},{"word":"looks","count":3},{"word":"near","count":3},{"word":"kinda","count":3},{"word":"eyes","count":3},{"word":"linghan","count":3},{"word":"discords","count":3},{"word":"hanging","count":3},{"word":"pretty","count":3},{"word":"walk","count":3},{"word":"probably","count":3},{"word":"better","count":3},{"word":"great","count":3},{"word":"resonance","count":3},{"word":"whole","count":3},{"word":"best","count":3},{"word":"heart","count":3},{"word":"field","count":3},{"word":"actually","count":3},{"word":"td","count":3},{"word":"today","count":3},{"word":"terminal","count":3},{"word":"try","count":3},{"word":"spicy","count":3},{"word":"absorbed","count":3},{"word":"though","count":3},{"word":"old","count":3},{"word":"happen","count":3},{"word":"ago","count":3},{"word":"longer","count":3},{"word":"safe","count":3},{"word":"hang","count":3},{"word":"hold","count":3},{"word":"promise","count":3},{"word":"flavor","count":3},{"word":"next","count":3},{"word":"friend","count":3},{"word":"else","count":3},{"word":"medley","count":3},{"word":"fancy","count":3},{"word":"brewed","count":3},{"word":"finest","count":3},{"word":"mahe","count":3},{"word":"recipe","count":3},{"word":"pyrite","count":3},{"word":"bit","count":3},{"word":"makes","count":3},{"word":"share","count":3},{"word":"ongoing","count":2},{"word":"recently","count":2},{"word":"vanished","count":2},{"word":"military","count":2},{"word":"watch","count":2},{"word":"count","count":2},{"word":"whoa","count":2},{"word":"fine","count":2},{"word":"guys","count":2},{"word":"fractsidus","count":2},{"word":"nothing","count":2},{"word":"care","count":2},{"word":"huaxu","count":2},{"word":"academy","count":2},{"word":"guy","count":2},{"word":"wake","count":2},{"word":"aftereffects","count":2},{"word":"making","count":2},{"word":"illegal","count":2},{"word":"quite","count":2},{"word":"quick","count":2},{"word":"hearing","count":2},{"word":"uhhh","count":2},{"word":"ju","count":2},{"word":"decided","count":2},{"word":"top-notch","count":2},{"word":"madam","count":2},{"word":"uh","count":2},{"word":"ancient","count":2},{"word":"shores","count":2},{"word":"loves","count":2},{"word":"gosh","count":2},{"word":"wore","count":2},{"word":"hand","count":2},{"word":"perfect","count":2},{"word":"keeps","count":2},{"word":"talk","count":2},{"word":"eye","count":2},{"word":"girl","count":2},{"word":"found","count":2},{"word":"sir","count":2},{"word":"plan","count":2},{"word":"supervisor","count":2},{"word":"cough","count":2},{"word":"amazing","count":2},{"word":"my-unwavering-love","count":2},{"word":"needs","count":2},{"word":"training","count":2},{"word":"grounds","count":2},{"word":"admit","count":2},{"word":"faster","count":2},{"word":"earth","count":2},{"word":"hurry","count":2},{"word":"huge","count":2},{"word":"gourd","count":2},{"word":"waste","count":2},{"word":"guide","count":2},{"word":"means","count":2},{"word":"etheric","count":2},{"word":"outta","count":2},{"word":"questions","count":2},{"word":"together","count":2},{"word":"short","count":2},{"word":"barrier","count":2},{"word":"agreed","count":2},{"word":"'round","count":2},{"word":"straight","count":2},{"word":"popular","count":2},{"word":"hero","count":2},{"word":"mastermind","count":2},{"word":"trope","count":2},{"word":"villain","count":2},{"word":"common","count":2},{"word":"researchers","count":2},{"word":"absorb","count":2},{"word":"ones","count":2},{"word":"sweet","count":2},{"word":"power","count":2},{"word":"along","count":2},{"word":"ability","count":2},{"word":"eating","count":2},{"word":"heard","count":2},{"word":"curious","count":2},{"word":"world","count":2},{"word":"history","count":2},{"word":"hope","count":2},{"word":"pages","count":2},{"word":"legend","count":2},{"word":"live","count":2},{"word":"years","count":2},{"word":"whether","count":2},{"word":"tds","count":2},{"word":"piece","count":2},{"word":"message","count":2},{"word":"ready","count":2},{"word":"take","count":2},{"word":"met","count":2},{"word":"patrol","count":2},{"word":"invite","count":2},{"word":"investigate","count":2},{"word":"new","count":2},{"word":"patrollers","count":2},{"word":"trouble","count":2},{"word":"talking","count":2},{"word":"calling","count":2},{"word":"treating","count":2},{"word":"nice","count":2},{"word":"adventure","count":2},{"word":"restaurant","count":2},{"word":"poached","count":2},{"word":"chicken","count":2},{"word":"cuisine","count":2},{"word":"gourmet","count":2},{"word":"waiting","count":2},{"word":"finally","count":2},{"word":"trust","count":2},{"word":"aw","count":2},{"word":"feast","count":2},{"word":"treat","count":2},{"word":"magic","count":2},{"word":"anywhere","count":2},{"word":"bring","count":2},{"word":"stomach","count":2},{"word":"mean","count":2},{"word":"safety","count":2},{"word":"golden-handled","count":2},{"word":"covered","count":2},{"word":"says","count":2},{"word":"koko","count":2},{"word":"mentioned","count":2},{"word":"wonder","count":2},{"word":"sense","count":2},{"word":"shop","count":2},{"word":"materials","count":2},{"word":"quality","count":2},{"word":"friends","count":2},{"word":"shooting","count":2},{"word":"single","count":2},{"word":"grub","count":2},{"word":"came","count":2},{"word":"sleeping","count":2},{"word":"invincible","count":2},{"word":"sound","count":2},{"word":"past","count":2},{"word":"taoyuan","count":2},{"word":"vale","count":2},{"word":"write","count":2},{"word":"wishes","count":2},{"word":"reaction","count":1},{"word":"getting","count":1},{"word":"persons","count":1},{"word":"reports","count":1},{"word":"nobody","count":1},{"word":"assaulted","count":1},{"word":"served","count":1},{"word":"weird","count":1},{"word":"suspicious","count":1},{"word":"sus","count":1},{"word":"laterz","count":1},{"word":"hell","count":1},{"word":"you-you","count":1},{"word":"lower","count":1},{"word":"weapons","count":1},{"word":"ance","count":1},{"word":"society","count":1},{"word":"statement","count":1},{"word":"helped","count":1},{"word":"somehow","count":1},{"word":"involved","count":1},{"word":"luckily","count":1},{"word":"man's","count":1},{"word":"custody","count":1},{"word":"suspect","count":1},{"word":"lady","count":1},{"word":"zero","count":1},{"word":"info","count":1},{"word":"varying","count":1},{"word":"degrees","count":1},{"word":"overclocking","count":1},{"word":"urgent","count":1},{"word":"professionals","count":1},{"word":"named","count":1},{"word":"lirong","count":1},{"word":"worst","count":1},{"word":"coma","count":1},{"word":"yesterday","count":1},{"word":"recovering","count":1},{"word":"progress","count":1},{"word":"cases","count":1},{"word":"led","count":1},{"word":"cult-like","count":1},{"word":"organization","count":1},{"word":"bunch","count":1},{"word":"twisted","count":1},{"word":"plans","count":1},{"word":"unbelievable","count":1},{"word":"toast","count":1},{"word":"specific","count":1},{"word":"whoever","count":1},{"word":"unusual","count":1},{"word":"later","count":1},{"word":"awkward","count":1},{"word":"showing","count":1},{"word":"cute","count":1},{"word":"jerks","count":1},{"word":"connection","count":1},{"word":"idea","count":1},{"word":"doctor","count":1},{"word":"woah","count":1},{"word":"ways","count":1},{"word":"picking","count":1},{"word":"candidates","count":1},{"word":"surprised","count":1},{"word":"lie","count":1},{"word":"lord","count":1},{"word":"choose","count":1},{"word":"previous","count":1},{"word":"magistrates","count":1},{"word":"jinhsi","count":1},{"word":"well-oiled","count":1},{"word":"machine","count":1},{"word":"i'd","count":1},{"word":"mental","count":1},{"word":"overclock","count":1},{"word":"paperwork","count":1},{"word":"gold","count":1},{"word":"loses","count":1},{"word":"shine","count":1},{"word":"norfall","count":1},{"word":"barrens","count":1},{"word":"battlefield","count":1},{"word":"times","count":1},{"word":"bell","count":1},{"word":"map","count":1},{"word":"flowers","count":1},{"word":"blush","count":1},{"word":"listening","count":1},{"word":"storytellers","count":1},{"word":"hi","count":1},{"word":"verina","count":1},{"word":"told","count":1},{"word":"learned","count":1},{"word":"anyone","count":1},{"word":"wearing","count":1},{"word":"automatically","count":1},{"word":"become","count":1},{"word":"immediately","count":1},{"word":"ohh","count":1},{"word":"tsk","count":1},{"word":"mysterious","count":1},{"word":"whenever","count":1},{"word":"rushing","count":1},{"word":"timing","count":1},{"word":"guy's","count":1},{"word":"sniffin'","count":1},{"word":"elderly","count":1},{"word":"minors","count":1},{"word":"keeping","count":1},{"word":"kept","count":1},{"word":"turning","count":1},{"word":"head","count":1},{"word":"nowhere","count":1},{"word":"fishy","count":1},{"word":"fixed","count":1},{"word":"location","count":1},{"word":"hmph","count":1},{"word":"organizational","count":1},{"word":"accreditation","count":1},{"word":"clear","count":1},{"word":"id","count":1},{"word":"number","count":1},{"word":"buy","count":1},{"word":"leave","count":1},{"word":"alone","count":1},{"word":"hello","count":1},{"word":"encore","count":1},{"word":"picture","count":1},{"word":"friggin","count":1},{"word":"grandpa","count":1},{"word":"jingzhu","count":1},{"word":"ringing","count":1},{"word":"bells","count":1},{"word":"ran","count":1},{"word":"snagging","count":1},{"word":"hence","count":1},{"word":"swing","count":1},{"word":"sec","count":1},{"word":"nailed","count":1},{"word":"mastering","count":1},{"word":"tuners","count":1},{"word":"wondering","count":1},{"word":"seemed","count":1},{"word":"ease","count":1},{"word":"wild","count":1},{"word":"midnight","count":1},{"word":"ranger","count":1},{"word":"totally","count":1},{"word":"clicks","count":1},{"word":"track","count":1},{"word":"gone","count":1},{"word":"cave","count":1},{"word":"places","count":1},{"word":"frustrating","count":1},{"word":"upgraded","count":1},{"word":"search","count":1},{"word":"function","count":1},{"word":"nearby","count":1},{"word":"straightforward","count":1},{"word":"normally","count":1},{"word":"afford","count":1},{"word":"dangerous","count":1},{"word":"soon","count":1},{"word":"terminals","count":1},{"word":"gourds","count":1},{"word":"service","count":1},{"word":"sea's","count":1},{"word":"influence","count":1},{"word":"send","count":1},{"word":"receive","count":1},{"word":"messages","count":1},{"word":"gathering","count":1},{"word":"recall","count":1},{"word":"full","count":1},{"word":"scoop","count":1},{"word":"detail","count":1},{"word":"get-go","count":1},{"word":"gorge","count":1},{"word":"reach","count":1},{"word":"safest","count":1},{"word":"round","count":1},{"word":"nexus","count":1},{"word":"provides","count":1},{"word":"coverage","count":1},{"word":"besides","count":1},{"word":"protective","count":1},{"word":"fortifications","count":1},{"word":"cities","count":1},{"word":"appeared","count":1},{"word":"blink","count":1},{"word":"sea","count":1},{"word":"following","count":1},{"word":"collect","count":1},{"word":"samples","count":1},{"word":"accordin'","count":1},{"word":"shows","count":1},{"word":"plays","count":1},{"word":"yes","count":1},{"word":"chance","count":1},{"word":"could've","count":1},{"word":"set","count":1},{"word":"bait","count":1},{"word":"simple-minded","count":1},{"word":"group","count":1},{"word":"schemes","count":1},{"word":"another","count":1},{"word":"gentle","count":1},{"word":"quiet","count":1},{"word":"hiding","count":1},{"word":"protagonist's","count":1},{"word":"nose","count":1},{"word":"dormant","count":1},{"word":"energetic","count":1},{"word":"handled","count":1},{"word":"spirited","count":1},{"word":"hurt","count":1},{"word":"goodness","count":1},{"word":"darn","count":1},{"word":"lay","count":1},{"word":"finger","count":1},{"word":"called","count":1},{"word":"looked","count":1},{"word":"fiamma's","count":1},{"word":"killer","count":1},{"word":"aww","count":1},{"word":"c'mon","count":1},{"word":"modest","count":1},{"word":"took","count":1},{"word":"fella","count":1},{"word":"couple","count":1},{"word":"kicks","count":1},{"word":"thin","count":1},{"word":"air","count":1},{"word":"elite","count":1},{"word":"class","count":1},{"word":"lucky","count":1},{"word":"pangu","count":1},{"word":"gourd-shaped","count":1},{"word":"device","count":1},{"word":"resonator","count":1},{"word":"developed","count":1},{"word":"limit","count":1},{"word":"absorbing","count":1},{"word":"start","count":1},{"word":"smaller","count":1},{"word":"tackling","count":1},{"word":"baby","count":1},{"word":"roseshrooms","count":1},{"word":"playin'","count":1},{"word":"fool","count":1},{"word":"tricks","count":1},{"word":"sleeve","count":1},{"word":"grilling","count":1},{"word":"alive","count":1},{"word":"indeed","count":1},{"word":"tried","count":1},{"word":"cook","count":1},{"word":"gulpuffs","count":1},{"word":"local","count":1},{"word":"speciality","count":1},{"word":"gulpuff's","count":1},{"word":"type","count":1},{"word":"held","count":1},{"word":"universe","count":1},{"word":"bare","count":1},{"word":"powerful","count":1},{"word":"turned","count":1},{"word":"rebuild","count":1},{"word":"sort","count":1},{"word":"laws","count":1},{"word":"began","count":1},{"word":"tales","count":1},{"word":"parents","count":1},{"word":"sentinel's","count":1},{"word":"appointment","count":1},{"word":"yangyang's","count":1},{"word":"impressive","count":1},{"word":"memory","count":1},{"word":"texts","count":1},{"word":"roughly","count":1},{"word":"story's","count":1},{"word":"reciting","count":1},{"word":"beggin'","count":1},{"word":"takin'","count":1},{"word":"school","count":1},{"word":"recite","count":1},{"word":"made-up","count":1},{"word":"eons","count":1},{"word":"'bout","count":1},{"word":"hundred","count":1},{"word":"known","count":1},{"word":"stretches","count":1},{"word":"thousand","count":1},{"word":"story","count":1},{"word":"exist","count":1},{"word":"rover's","count":1},{"word":"great-great-great-great-great-","count":1},{"word":"granddaddy","count":1},{"word":"granny","count":1},{"word":"distance","count":1},{"word":"reaches","count":1},{"word":"moves","count":1},{"word":"sharp","count":1},{"word":"dealing","count":1},{"word":"park","count":1},{"word":"keepin'","count":1},{"word":"nevermind","count":1},{"word":"title","count":1},{"word":"rest","count":1},{"word":"assured","count":1},{"word":"travels","count":1},{"word":"victory","count":1},{"word":"prevail","count":1},{"word":"lasting","count":1},{"word":"night","count":1},{"word":"pre-recorded","count":1},{"word":"broadcast","count":1},{"word":"devise","count":1},{"word":"emergency","count":1},{"word":"wave","count":1},{"word":"attacks","count":1},{"word":"boy","count":1},{"word":"amount","count":1},{"word":"insane","count":1},{"word":"would've","count":1},{"word":"taken","count":1},{"word":"handle","count":1},{"word":"director","count":1},{"word":"taoqi","count":1},{"word":"run","count":1},{"word":"situation","count":1},{"word":"gate","count":1},{"word":"sonance","count":1},{"word":"casket","count":1},{"word":"acquaintance","count":1},{"word":"relic","count":1},{"word":"merchant","count":1},{"word":"brings","count":1},{"word":"ages","count":1},{"word":"station's","count":1},{"word":"busy","count":1},{"word":"lately","count":1},{"word":"zhezhi's","count":1},{"word":"hiya","count":1},{"word":"moon-chasing","count":1},{"word":"painting","count":1},{"word":"put","count":1},{"word":"wall","count":1},{"word":"formally","count":1},{"word":"bout'","count":1},{"word":"heading","count":1},{"word":"get-together","count":1},{"word":"support","count":1},{"word":"assault","count":1},{"word":"mine","count":1},{"word":"odd","count":1},{"word":"monsters","count":1},{"word":"caused","count":1},{"word":"witnesses","count":1},{"word":"triggered","count":1},{"word":"incident","count":1},{"word":"stirring","count":1},{"word":"sorry","count":1},{"word":"ya","count":1},{"word":"free","count":1},{"word":"biggie","count":1},{"word":"diving","count":1},{"word":"tokens","count":1},{"word":"figured","count":1},{"word":"cash","count":1},{"word":"takes","count":1},{"word":"maocai","count":1},{"word":"cooks","count":1},{"word":"explosion","count":1},{"word":"spice","count":1},{"word":"gulp","count":1},{"word":"feel","count":1},{"word":"buzz","count":1},{"word":"bones","count":1},{"word":"pressure","count":1},{"word":"genius","count":1},{"word":"whipping","count":1},{"word":"treats","count":1},{"word":"rising","count":1},{"word":"loong","count":1},{"word":"authentic","count":1},{"word":"expect","count":1},{"word":"foodie","count":1},{"word":"tasty","count":1},{"word":"date","count":1},{"word":"time-wise","count":1},{"word":"eagerly","count":1},{"word":"ah","count":1},{"word":"dilly-dally","count":1},{"word":"munch","count":1},{"word":"comes","count":1},{"word":"dive","count":1},{"word":"ordering","count":1},{"word":"kick-start","count":1},{"word":"forget","count":1},{"word":"begging","count":1},{"word":"brought","count":1},{"word":"experience","count":1},{"word":"candied","count":1},{"word":"caltrops","count":1},{"word":"fresh","count":1},{"word":"sweetness","count":1},{"word":"sauce","count":1},{"word":"original","count":1},{"word":"unmatched","count":1},{"word":"stew","count":1},{"word":"tasted","count":1},{"word":"miss","count":1},{"word":"paid","count":1},{"word":"broke","count":1},{"word":"cater","count":1},{"word":"appetites","count":1},{"word":"rolled","count":1},{"word":"small","count":1},{"word":"portion","count":1},{"word":"menu","count":1},{"word":"fantastic","count":1},{"word":"flavors","count":1},{"word":"less","count":1},{"word":"fret","count":1},{"word":"over-ordering","count":1},{"word":"enjoying","count":1},{"word":"pals","count":1},{"word":"shake","count":1},{"word":"polished","count":1},{"word":"plate","count":1},{"word":"room","count":1},{"word":"second","count":1},{"word":"buds","count":1},{"word":"tingling","count":1},{"word":"peculiar","count":1},{"word":"remind","count":1},{"word":"sweetest","count":1},{"word":"supposed","count":1},{"word":"obviously","count":1},{"word":"tabs","count":1},{"word":"cut","count":1},{"word":"chase","count":1},{"word":"handed","count":1},{"word":"mon","count":1},{"word":"wrack","count":1},{"word":"brain","count":1},{"word":"thinks","count":1},{"word":"medicinal","count":1},{"word":"regular","count":1},{"word":"dish","count":1},{"word":"reputation","count":1},{"word":"i-i","count":1},{"word":"choice","count":1},{"word":"rules","count":1},{"word":"slow","count":1},{"word":"join","count":1},{"word":"puzzle","count":1},{"word":"crack","count":1},{"word":"figuring","count":1},{"word":"hit","count":1},{"word":"mark","count":1},{"word":"guessed","count":1},{"word":"oops","count":1},{"word":"step","count":1},{"word":"role","count":1},{"word":"encyclopedia","count":1},{"word":"ground","count":1},{"word":"strolls","count":1},{"word":"trek","count":1},{"word":"thrilled","count":1},{"word":"hometown","count":1},{"word":"nearing","count":1},{"word":"main","count":1},{"word":"things","count":1},{"word":"interesting","count":1},{"word":"xiaofang","count":1},{"word":"doomed","count":1},{"word":"recreate","count":1},{"word":"stir","count":1},{"word":"starts","count":1},{"word":"bubbling","count":1},{"word":"exact","count":1},{"word":"passed","count":1},{"word":"word","count":1},{"word":"mouth","count":1},{"word":"sparking","count":1},{"word":"debates","count":1},{"word":"shopping","count":1},{"word":"list","count":1},{"word":"detailed","count":1},{"word":"absolutely","count":1},{"word":"household","count":1},{"word":"pulled","count":1},{"word":"secret","count":1},{"word":"stash","count":1},{"word":"brew","count":1},{"word":"divine","count":1},{"word":"require","count":1},{"word":"cooking","count":1},{"word":"techniques","count":1},{"word":"reviews","count":1},{"word":"bogus","count":1},{"word":"eager","count":1},{"word":"knowing","count":1},{"word":"backstory","count":1},{"word":"mind","count":1},{"word":"lending","count":1},{"word":"standby","count":1},{"word":"lend","count":1},{"word":"maker","count":1},{"word":"weapon-related","count":1},{"word":"maintenance","count":1},{"word":"deal","count":1},{"word":"synthesizer","count":1},{"word":"aside","count":1},{"word":"crafting","count":1},{"word":"beefing","count":1},{"word":"basic","count":1},{"word":"potions","count":1},{"word":"one-stop","count":1},{"word":"kicking","count":1},{"word":"synthesis","count":1},{"word":"ahead","count":1},{"word":"seem","count":1},{"word":"tricky","count":1},{"word":"hands-on","count":1},{"word":"almost","count":1},{"word":"half","count":1},{"word":"tiring","count":1},{"word":"worth","count":1},{"word":"usually","count":1},{"word":"tied","count":1},{"word":"patrols","count":1},{"word":"catching","count":1},{"word":"total","count":1},{"word":"introducing","count":1},{"word":"breeze","count":1},{"word":"reconnecting","count":1},{"word":"end","count":1},{"word":"tour","count":1},{"word":"buddy","count":1},{"word":"instead","count":1},{"word":"rave","count":1},{"word":"distilled","count":1},{"word":"bowl","count":1},{"word":"treasure","count":1},{"word":"lies","count":1},{"word":"willingness","count":1},{"word":"prized","count":1},{"word":"wartime","count":1},{"word":"reminding","count":1},{"word":"eat","count":1},{"word":"caring","count":1},{"word":"fretting","count":1},{"word":"dropping","count":1},{"word":"knowledge","count":1},{"word":"bombs","count":1},{"word":"doubt","count":1},{"word":"open","count":1},{"word":"pantries","count":1},{"word":"cherished","count":1},{"word":"protect","count":1},{"word":"soul","count":1},{"word":"including","count":1},{"word":"shoulder","count":1},{"word":"troubles","count":1},{"word":"determination","count":1},{"word":"talks","count":1},{"word":"data","count":1},{"word":"dump","count":1},{"word":"duper","count":1},{"word":"nah","count":1},{"word":"extra","count":1},{"word":"boost","count":1},{"word":"ego","count":1},{"word":"confirmed","count":1},{"word":"lying","count":1},{"word":"inside","count":1},{"word":"crazy","count":1},{"word":"anything's","count":1},{"word":"possible","count":1},{"word":"reverberations","count":1},{"word":"stumbled","count":1},{"word":"upon","count":1},{"word":"soaked","count":1},{"word":"sponge","count":1},{"word":"feasible","count":1},{"word":"sooo","count":1},{"word":"lost","count":1},{"word":"memories","count":1},{"word":"happenings","count":1},{"word":"fighting","count":1},{"word":"different","count":1},{"word":"usual","count":1},{"word":"turns","count":1},{"word":"denomination","count":1},{"word":"nick","count":1},{"word":"everyone's","count":1},{"word":"difference","count":1},{"word":"play","count":1},{"word":"character","count":1},{"word":"transformation","count":1},{"word":"fly","count":1},{"word":"ears","count":1},{"word":"righteous","count":1},{"word":"raptor","count":1},{"word":"valor","count":1},{"word":"hawk","count":1},{"word":"flying","count":1},{"word":"fury","count":1},{"word":"wrong","count":1},{"word":"muttering","count":1},{"word":"abra","count":1},{"word":"reading","count":1},{"word":"spell","count":1},{"word":"hoping","count":1},{"word":"answers","count":1},{"word":"square","count":1},{"word":"lead","count":1},{"word":"starting","count":1},{"word":"point","count":1},{"word":"uncover","count":1},{"word":"asking","count":1},{"word":"unsure","count":1},{"word":"learn","count":1},{"word":"shape","count":1},{"word":"yet","count":1},{"word":"easy","count":1},{"word":"mr","count":1},{"word":"xiangli","count":1},{"word":"yao","count":1},{"word":"entire","count":1},{"word":"thorough","count":1},{"word":"examination","count":1},{"word":"protects","count":1},{"word":"course","count":1},{"word":"face","count":1},{"word":"hole","count":1},{"word":"shy","count":1},{"word":"feelin'","count":1},{"word":"lonely","count":1},{"word":"fireworks","count":1},{"word":"moon","count":1},{"word":"corner","count":1},{"word":"caught","count":1},{"word":"lanterns","count":1},{"word":"hall","count":1},{"word":"alley","count":1},{"word":"glowing","count":1},{"word":"lit","count":1},{"word":"traditions","count":1},{"word":"onto","count":1},{"word":"paper","count":1},{"word":"branches","count":1},{"word":"toss","count":1},{"word":"moontree","count":1},{"word":"lodge","count":1},{"word":"works","count":1},{"word":"charm","count":1},{"word":"wish","count":1},{"word":"simple","count":1}],"lines":[{"text":"Huh? Is <i>that</i> your first reaction? Come on!","quest_name":"Solitary Path","quest_id":114000018},{"text":"Anyway! You know, we could really use your help with this ongoing case!","quest_name":"Solitary Path","quest_id":114000018},{"text":"Here's the thing, we could really use your help with this ongoing case...","quest_name":"Solitary Path","quest_id":114000018},{"text":"We've been getting a lot of missing persons reports recently.","quest_name":"Solitary Path","quest_id":114000018},{"text":"Nobody ever saw those people assaulted or anything, they just vanished.","quest_name":"Solitary Path","quest_id":114000018},{"text":"Some of those people are even Resonators or they've served in the military!","quest_name":"Solitary Path","quest_id":114000018},{"text":"Since you're always coming and going from the city, can you help me watch out for anything weird or suspicious?","quest_name":"Solitary Path","quest_id":114000018},{"text":"Thank you so much! Knew I could count on you!","quest_name":"Solitary Path","quest_id":114000018},{"text":"Ring me up when you spot anything sus, yeah? Laterz!","quest_name":"Solitary Path","quest_id":114000018},{"text":"Hey! Who the hell are you? Let {Male=him;Female=her} go!","quest_name":"Solitary Path","quest_id":114000018},{"text":"Whoa! You-You... Don't move!","quest_name":"Solitary Path","quest_id":114000018},{"text":"Ugh, fine... Lower your weapons guys!","quest_name":"Solitary Path","quest_id":114000018},{"text":"So that's what the Séance Society was up to... Thanks for your statement, it really helped!","quest_name":"Solitary Path","quest_id":114000018},{"text":"Somehow the Fractsidus was involved too! Who could have thought… Luckily you were there to stop them in time!","quest_name":"Solitary Path","quest_id":114000018},{"text":"The man's still not saying anything... Guess we'll have to keep him under custody for now.","quest_name":"Solitary Path","quest_id":114000018},{"text":"Nothing about that suspect lady either. We still have zero info on her.","quest_name":"Solitary Path","quest_id":114000018},{"text":"Most of those Resonators have varying degrees of Overclocking. They need urgent care, the professionals from Huaxu Academy are already on it.","quest_name":"Solitary Path","quest_id":114000018},{"text":"A guy named Lirong had it worst, didn't wake up from his coma until yesterday.","quest_name":"Solitary Path","quest_id":114000018},{"text":"He's still recovering from some really bad aftereffects, but at least he's making progress.","quest_name":"Solitary Path","quest_id":114000018},{"text":"Oh, so the missing cases led to an illegal cult-like organization AND a bunch of other twisted plans!","quest_name":"Solitary Path","quest_id":114000018},{"text":"Unbelievable... We'd be toast without your help.","quest_name":"Solitary Path","quest_id":114000018},{"text":"Huh? And who's that?","quest_name":"Solitary Path","quest_id":114000018},{"text":"What? Come on, you need to be more specific… Whoever they are, sounds like they'll make for quite the Patroller.","quest_name":"Solitary Path","quest_id":114000018},{"text":"Well, that's it for now. Ring me up when you find something unusual again. I'll catch you later!","quest_name":"Solitary Path","quest_id":114000018},{"text":"There you are, Rover!","quest_name":"Rewinding Raindrops","quest_id":114000020},{"text":"It's just Baizhi being Baizhi. She's a little awkward with showing care, but I think it's cute!","quest_name":"Rewinding Raindrops","quest_id":114000020},{"text":"Anyway! Rover, quick, tell us what happened!","quest_name":"Rewinding Raindrops","quest_id":114000020},{"text":"The Fractsidus again? Ugh, those jerks!","quest_name":"Rewinding Raindrops","quest_id":114000020},{"text":"Connection? ...No idea, but I did hear General Jiyan used to be a military doctor...","quest_name":"Rewinding Raindrops","quest_id":114000020},{"text":"Woah. First time hearing about all that...","quest_name":"Rewinding Raindrops","quest_id":114000020},{"text":"Uhhh... Maybe the Sentinel had its own special ways of picking candidates?","quest_name":"Rewinding Raindrops","quest_id":114000020},{"text":"Yeah, true. Wouldn't be surprised if Jué decided to make me the Magistrate one day, not gonna lie!","quest_name":"Rewinding Raindrops","quest_id":114000020},{"text":"Seriously, Lord Jué knows how to choose 'em. Our previous Magistrates were all top-notch at running the show.","quest_name":"Rewinding Raindrops","quest_id":114000020},{"text":"And Madam Jinhsi? She's already made this city a well-oiled machine in no time.","quest_name":"Rewinding Raindrops","quest_id":114000020},{"text":"I'd have a mental Overclock just trying to keep up with all that paperwork... She was made for this!","quest_name":"Rewinding Raindrops","quest_id":114000020},{"text":"Uh, what is that saying again? Real gold never loses its shine!","quest_name":"Rewinding Raindrops","quest_id":114000020},{"text":"The Norfall Barrens?! It's been a battlefield since ancient times...","quest_name":"Rewinding Raindrops","quest_id":114000020},{"text":"The Black Shores? Doesn't ring a bell... Sounds like the name of a place, but I've never seen it on any map.","quest_name":"Rewinding Raindrops","quest_id":114000020},{"text":"Since it's about flowers... We should go ask Grandma Lin!","quest_name":"Rewinding Raindrops","quest_id":114000020},{"text":"Hehe... You're making me blush a little.","quest_name":"Rewinding Raindrops","quest_id":114000020},{"text":"Grandma Lin loves listening to storytellers. I think I saw her earlier... Let's go look for her.","quest_name":"Rewinding Raindrops","quest_id":114000020},{"text":"Hi, Verina! I'm Chixia, this is Yangyang, and {Male=he;Female=she}'s Rover! Grandma Lin told us we should come find you!","quest_name":"Rewinding Raindrops","quest_id":114000020},{"text":"Wow, you really know your stuff! I learned a lot from that!","quest_name":"Rewinding Raindrops","quest_id":114000020},{"text":"Gosh, help us out, someone! We don't know what kind of flower it is, and we haven't seen anyone wearing it either...","quest_name":"Rewinding Raindrops","quest_id":114000020},{"text":"Speaking of that... How does it even work? If I wore this flower on me right now, do I automatically become one of them?","quest_name":"Rewinding Raindrops","quest_id":114000020},{"text":"Uhhh... Yeah? I was just saying if I wore this flower, would they immediately see me as one of their own...","quest_name":"Rewinding Raindrops","quest_id":114000020},{"text":"Ohh, I see... but how do we get our hands on one?","quest_name":"Rewinding Raindrops","quest_id":114000020},{"text":"Rover, did you find them?","quest_name":"Rewinding Raindrops","quest_id":114000020},{"text":"What? Seriously? No way...","quest_name":"Rewinding Raindrops","quest_id":114000020},{"text":"No way, are they really from the Black Shores?","quest_name":"Rewinding Raindrops","quest_id":114000020},{"text":"Tsk... Not as mysterious as people make 'em out to be. Well at least they're good at running, I'll give them that.","quest_name":"Rewinding Raindrops","quest_id":114000020},{"text":"Don't worry, Yangyang. We all know how strong our Rover is!","quest_name":"Rewinding Raindrops","quest_id":114000020},{"text":"Just ring us whenever you need a hand! We'll come rushing!","quest_name":"Rewinding Raindrops","quest_id":114000020},{"text":"Rover, perfect timing! This guy's been sniffin' around here for a while now. He keeps trying to talk to the elderly and minors! I've been keeping an eye on him!","quest_name":"Rewinding Raindrops","quest_id":114000020},{"text":"And I saw a little girl with him! She kept turning her head and looking around, but now she's nowhere to be found. This is super fishy!","quest_name":"Rewinding Raindrops","quest_id":114000020},{"text":"Hey, I'm Patroller Chixia. Sir, business license, please.","quest_name":"Rewinding Raindrops","quest_id":114000020},{"text":"I see. So, no license. I bet you don't have a fixed business location either, huh?","quest_name":"Rewinding Raindrops","quest_id":114000020},{"text":"Hmph, now show me your Organizational Accreditation, please.","quest_name":"Rewinding Raindrops","quest_id":114000020},{"text":"No license, no clear business plan... You're running an illegal business, then...","quest_name":"Rewinding Raindrops","quest_id":114000020},{"text":"Who's your supervisor? You should at least have their ID number?","quest_name":"Rewinding Raindrops","quest_id":114000020},{"text":"So do you even have a supervisor or not?","quest_name":"Rewinding Raindrops","quest_id":114000020},{"text":"Yeah, yeah! I believe you! I know what's going on!","quest_name":"Rewinding Raindrops","quest_id":114000020},{"text":"Now, sir, you're coming with me to the Patroller Station!","quest_name":"Rewinding Raindrops","quest_id":114000020},{"text":"You really think I'm gonna buy that?","quest_name":"Rewinding Raindrops","quest_id":114000020},{"text":"Back off! Leave that girl alone!","quest_name":"Rewinding Raindrops","quest_id":114000020},{"text":"Hello, little one. Is your name Encore? Do you know this person?","quest_name":"Rewinding Raindrops","quest_id":114000020},{"text":"We've got your back, little one! No worries! Just tell us what you know!","quest_name":"Rewinding Raindrops","quest_id":114000020},{"text":"Cough cough... Wait!","quest_name":"Rewinding Raindrops","quest_id":114000020},{"text":"No way? That's amazing, seriously! It looks exactly like the flower in that picture!","quest_name":"Rewinding Raindrops","quest_id":114000020},{"text":"It's friggin amazing! Could you do that again? Please! I love it!","quest_name":"Rewinding Raindrops","quest_id":114000020},{"text":"Hey there, Rover! Remember Grandpa Jingzhu?","quest_name":"Silver-haired Echo Trainer - II","quest_id":139000020},{"text":"Yep, the one who said that “my-unwavering-love” thing.","quest_name":"Silver-haired Echo Trainer - II","quest_id":139000020},{"text":"The one who said that \"my-unwavering-love\" thing. Ringing any bells now?","quest_name":"Silver-haired Echo Trainer - II","quest_id":139000020},{"text":"So, I ran into him earlier, and he needs our help in snagging Echoes again. Hence, the call.","quest_name":"Silver-haired Echo Trainer - II","quest_id":139000020},{"text":"Awesome! We’ll catch you near the training grounds, then.","quest_name":"Silver-haired Echo Trainer - II","quest_id":139000020},{"text":"That’s fine. Swing by the training grounds when you’ve got a sec.","quest_name":"Silver-haired Echo Trainer - II","quest_id":139000020},{"text":"Nailed it! {PlayerName}, you’re really mastering this!","quest_name":"Silver-haired Echo Trainer - III","quest_id":139000021},{"text":"We did find some Tuners! I gotta admit, I was kinda wondering why you seemed so at ease out in the wild.","quest_name":"Silver-haired Echo Trainer - III","quest_id":139000021},{"text":"But now that I know you used to be a Midnight Ranger, it totally clicks!","quest_name":"Silver-haired Echo Trainer - III","quest_id":139000021},{"text":"Yep! The more eyes we have, the faster we can track down Grandma Linghan.","quest_name":"Silver-haired Echo Trainer - III","quest_id":139000021},{"text":"But where on earth could Grandma Linghan have gone...?","quest_name":"Silver-haired Echo Trainer - III","quest_id":139000021},{"text":"A cave, you say? Tacet Discords love hanging out in places like that. Let’s hurry and check it out!","quest_name":"Silver-haired Echo Trainer - III","quest_id":139000021},{"text":"This place is huge! How on earth are we going to find her? Ugh, it's so frustrating!","quest_name":"Silver-haired Echo Trainer - III","quest_id":139000021},{"text":"Yep! The gourd just got upgraded with a search function. Let’s see if we can use it to spot any nearby Tacet Discords.","quest_name":"Silver-haired Echo Trainer - III","quest_id":139000021},{"text":"Don’t worry, {PlayerName}, it’s pretty straightforward. Normally, I’d give you time to figure it out yourself, but with Grandma Linghan missing, we can’t afford to waste any. Let me walk you through it.","quest_name":"Silver-haired Echo Trainer - III","quest_id":139000021},{"text":"You got it! I’ll be your guide through this.","quest_name":"Silver-haired Echo Trainer - III","quest_id":139000021},{"text":"You can call me Chixia... And, she's Yangyang!","quest_name":"Utterance of Marvels: I","quest_id":139000025},{"text":"Baizhi didn't tell us you'd have these aftereffects when you wake up.","quest_name":"Utterance of Marvels: I","quest_id":139000025},{"text":"That means it's probably gonna get dangerous here soon.","quest_name":"Utterance of Marvels: I","quest_id":139000025},{"text":"Ugh, I knew it. Our <ano=Terminals>gourds</ano> are out of service because of the <color=Highlight>Etheric Sea's</color> influence. We can't send or receive messages for help now. We better hurry over to meet up with Baizhi at our gathering spot and get outta here.","quest_name":"Utterance of Marvels: I","quest_id":139000025},{"text":"Guess you really can't recall a thing, but don't worry!","quest_name":"Utterance of Marvels: I","quest_id":139000025},{"text":"If you got any questions, we can talk as we move. Yangyang and I will give you the full scoop, every little detail, from the get-go!","quest_name":"Utterance of Marvels: I","quest_id":139000025},{"text":"Oh, that's great! Let's go together!","quest_name":"Utterance of Marvels: I","quest_id":139000025},{"text":"Yeah, let's get going!","quest_name":"Utterance of Marvels: I","quest_id":139000025},{"text":"Once we're outta the gorge, there's only a short walk to reach Jinzhou!","quest_name":"Utterance of Marvels: I","quest_id":139000025},{"text":"Jinzhou is the safest place round here. The Resonance Nexus provides coverage for the whole city. Besides, we've got a protective barrier and strong fortifications!","quest_name":"Utterance of Marvels: I","quest_id":139000025},{"text":"Hehe, right?","quest_name":"Utterance of Marvels: I","quest_id":139000025},{"text":"Hehe, maybe it's not as big as some other cities. BUT! Jinzhou is always the best place in my heart!","quest_name":"Utterance of Marvels: I","quest_id":139000025},{"text":"Huh? We've agreed to meet up with Baizhi here... Where is she?","quest_name":"Utterance of Marvels: I","quest_id":139000025},{"text":"...A Tacet Field?","quest_name":"Utterance of Marvels: I","quest_id":139000025},{"text":"...When did it show up?","quest_name":"Utterance of Marvels: I","quest_id":139000025},{"text":"It wasn't here when we just got here.","quest_name":"Utterance of Marvels: I","quest_id":139000025},{"text":"So it appeared while we weren't looking? Like, in the blink of an eye?","quest_name":"Utterance of Marvels: I","quest_id":139000025},{"text":"Or maybe the Etheric Sea can tell where we are? Could it be following us?","quest_name":"Utterance of Marvels: I","quest_id":139000025},{"text":"Isn't that Baizhi?!","quest_name":"Utterance of Marvels: I","quest_id":139000025},{"text":"Baizhi!","quest_name":"Utterance of Marvels: I","quest_id":139000025},{"text":"BAIZHI!","quest_name":"Utterance of Marvels: I","quest_id":139000025},{"text":"We agreed to meet up 'round here, and she said she was off to collect some samples. Gosh, did she really go straight into the heart of a Tacet Field for that?!","quest_name":"Utterance of Marvels: I","quest_id":139000025},{"text":"Accordin' to the <ano=Popular Shows in Jinzhou>Hero Plays</ano>, yes! There's a chance for that!","quest_name":"Utterance of Marvels: I","quest_id":139000025},{"text":"True, who could've set the bait, then?","quest_name":"Utterance of Marvels: I","quest_id":139000025},{"text":"Oh, I see... the one who seems simple-minded in the group is actually the mastermind with schemes. That's another popular trope!","quest_name":"Utterance of Marvels: I","quest_id":139000025},{"text":"No, wait... I'm not the mastermind!","quest_name":"Utterance of Marvels: I","quest_id":139000025},{"text":"Oh, I see... the one who seems gentle and quiet is actually the villain, hiding right under the protagonist's nose. That's a common trope, too!","quest_name":"Utterance of Marvels: I","quest_id":139000025},{"text":"No, wait... Yangyang isn't the villain!","quest_name":"Utterance of Marvels: I","quest_id":139000025},{"text":"What?!","quest_name":"Utterance of Marvels: I","quest_id":139000025},{"text":"Baizhi!","quest_name":"Utterance of Marvels: I","quest_id":139000025},{"text":"Baizhi! We're in a Dormant Tacet Field, right? Why did you come here by yourself?","quest_name":"Utterance of Marvels: I","quest_id":139000025},{"text":"Baizhi, you know, we... huh?","quest_name":"Utterance of Marvels: I","quest_id":139000025},{"text":"You know, {Male=he;Female=she} was super energetic! Handled a super big TD! Way more spirited than me!","quest_name":"Utterance of Marvels: I","quest_id":139000025},{"text":"Yangyang! Rover!","quest_name":"Utterance of Marvels: I","quest_id":139000025},{"text":"Are you alright? Are you hurt?","quest_name":"Utterance of Marvels: I","quest_id":139000025},{"text":"Ugh thank goodness! We could see that darn barrier, but couldn't lay a finger on it!","quest_name":"Utterance of Marvels: I","quest_id":139000025},{"text":"Rover, what was that last move called? That looked as cool as Fiamma's killer move!","quest_name":"Utterance of Marvels: I","quest_id":139000025},{"text":"Aww c'mon, stop being modest! So you didn't even go all out earlier. I saw how you took down that fella with both of my eyes!","quest_name":"Utterance of Marvels: I","quest_id":139000025},{"text":"You made a couple kicks and that thing vanished into thin air!","quest_name":"Utterance of Marvels: I","quest_id":139000025},{"text":"Anyway, come check this out!","quest_name":"Utterance of Marvels: I","quest_id":139000025},{"text":"Wow! An Echo of the Elite Class... Someone got lucky today!","quest_name":"Utterance of Marvels: I","quest_id":139000025},{"text":"Oh, by Pangu Terminal, she means the gourd-shaped device every Resonator has, developed by researchers in Huanglong!","quest_name":"Utterance of Marvels: I","quest_id":139000025},{"text":"But you see, it's not always we get to find these. Also, there's a limit to what your gourd can absorb.","quest_name":"Utterance of Marvels: I","quest_id":139000025},{"text":"No need for that! Rover, why don't you just try absorbing it with your Terminal?","quest_name":"Utterance of Marvels: I","quest_id":139000025},{"text":"...Oh. So it doesn't work.","quest_name":"Utterance of Marvels: I","quest_id":139000025},{"text":"No worries! You can start with smaller ones before tackling this guy here.","quest_name":"Utterance of Marvels: I","quest_id":139000025},{"text":"There should be some sweet Baby Roseshrooms 'round here. Let's go check those out, shall we?","quest_name":"Utterance of Marvels: I","quest_id":139000025},{"text":"What... What kinda power is that!","quest_name":"Utterance of Marvels: I","quest_id":139000025},{"text":"Rover, you...","quest_name":"Utterance of Marvels: I","quest_id":139000025},{"text":"You been playin' the fool all along?","quest_name":"Utterance of Marvels: I","quest_id":139000025},{"text":"I've never seen a Resonance Ability quite like this. You got any other tricks up your sleeve? Like, eating a whole Tacet Discord? Grilling Echoes alive?","quest_name":"Utterance of Marvels: I","quest_id":139000025},{"text":"Wasn't it your Resonance Ability?","quest_name":"Utterance of Marvels: I","quest_id":139000025},{"text":"Indeed. So what would a Tacet Discord taste like? Spicy? Sweet?","quest_name":"Utterance of Marvels: I","quest_id":139000025},{"text":"I heard some folks tried to cook Gulpuffs, and they even made it a local speciality, didn't they?","quest_name":"Utterance of Marvels: I","quest_id":139000025},{"text":"Speaking of which, Gulpuff's a type of Tacet Discord, too!","quest_name":"Utterance of Marvels: I","quest_id":139000025},{"text":"I'm even more curious now... Anyway, spicy food is always the best!","quest_name":"Utterance of Marvels: I","quest_id":139000025},{"text":"There was a very strong person way back. Like they held the whole universe right in their hands. As there was no Terminal in those days, they absorbed the Tacet Discords with their bare hands!","quest_name":"Utterance of Marvels: I","quest_id":139000025},{"text":"and the TD they absorbed was the most powerful of all. That person turned it into the first Echo ever.","quest_name":"Utterance of Marvels: I","quest_id":139000025},{"text":"Then they used the power of that Echo to rebuild the world, sort out the laws, and that's how the history of Huanglong began...","quest_name":"Utterance of Marvels: I","quest_id":139000025},{"text":"Actually... I'm not, I hope I was though. That was just some old tales my parents used to tell me, kinda like the <i>Sentinel's Appointment</i> thing.","quest_name":"Utterance of Marvels: I","quest_id":139000025},{"text":"Yangyang's got an impressive memory for the ancient texts. Me? I just happen to roughly remember what the story's about.","quest_name":"Utterance of Marvels: I","quest_id":139000025},{"text":"Please, Yangyang, stop reciting that! I'm beggin' you!","quest_name":"Utterance of Marvels: I","quest_id":139000025},{"text":"Oh my, it's takin' me back to my school days, when I had to recite pages and pages of them... Anyway, that's just a made-up legend, isn't it?","quest_name":"Utterance of Marvels: I","quest_id":139000025},{"text":"Come on, that was eons ago. Us Resonators do live a little longer, but we're still looking at 'bout a hundred years or so. And the known history of Huanglong stretches back at least a thousand years...","quest_name":"Utterance of Marvels: I","quest_id":139000025},{"text":"Whether it's true or not, that story happened a long time ago when Jinzhou didn't even exist.","quest_name":"Utterance of Marvels: I","quest_id":139000025},{"text":"Could it be that Rover's like, the great-great-great-great-great-{Male=granddaddy;Female=granny} of us all?","quest_name":"Utterance of Marvels: I","quest_id":139000025},{"text":"There’s still some distance to the Huaxu Academy. Let’s see who reaches there faster!","quest_name":"First Resonance","quest_id":139000027},{"text":"Ugh... Please tell me this is the last one!","quest_name":"Grand Warstorm","quest_id":140000004},{"text":"Rover, your moves are sharp as always. Dealing with so many TDs seems like a walk in the park for you.","quest_name":"Grand Warstorm","quest_id":140000004},{"text":"Rover, Yangyang, I'll be keepin' the city safe as a Patroller. Do come back in one piece, okay?","quest_name":"Grand Warstorm","quest_id":140000004},{"text":"Thanks! I'll give it my all!","quest_name":"Grand Warstorm","quest_id":140000004},{"text":"Rover! I said don't call me that... Nevermind, we don't have time for this.","quest_name":"Grand Warstorm","quest_id":140000004},{"text":"Wow, thanks, Rover! Can't believe you still remember that title! I'll live up to it for sure!","quest_name":"Grand Warstorm","quest_id":140000004},{"text":"Rest assured. You can count on me!","quest_name":"Grand Warstorm","quest_id":140000004},{"text":"Rover, Yangyang, safe travels!","quest_name":"Grand Warstorm","quest_id":140000004},{"text":"May victory prevail the lasting night!","quest_name":"Grand Warstorm","quest_id":140000004},{"text":"It's a pre-recorded broadcast message. Our Magistrate saw this coming, and she had General Jiyan devise an emergency plan a long time ago.","quest_name":"Grand Warstorm","quest_id":140000004},{"text":"This wave of TD attacks should be over now.","quest_name":"Grand Warstorm","quest_id":140000004},{"text":"We knew this was coming and we were ready, but oh boy, the amount of TDs is insane.","quest_name":"Grand Warstorm","quest_id":140000004},{"text":"Thanks for coming in time, Rover. It would've taken us much longer to handle this.","quest_name":"Grand Warstorm","quest_id":140000004},{"text":"Oh, Director Taoqi is here too. For a better run down of the situation, you can find her near the city gate!","quest_name":"Grand Warstorm","quest_id":140000004},{"text":"Rover, it’s a <color=Highlight>Sonance Casket</color>! Hmm... Hang on to it. I know this old acquaintance who’s a <color=Highlight>relic merchant</color>. He knows a lot about stuff like this. I’ll take you to him when we get to Jinzhou.","quest_name":"Remnants of the Past Days","quest_id":310000040},{"text":"Hmm? {PlayerName}? Hey! {PlayerName}!","quest_name":"True Colors","quest_id":311000000},{"text":"What brings you here? It's been ages since we last met! The Patrol Station's been pretty busy lately, so I haven't had the time to catch up with you.","quest_name":"True Colors","quest_id":311000000},{"text":"And Zhezhi's here too! Hiya! Do you remember me? We met at the Moon-Chasing Festival.","quest_name":"True Colors","quest_id":311000000},{"text":"Oh? Are you alright? You don't look well... Do you need help?","quest_name":"True Colors","quest_id":311000000},{"text":"The painting we had you do for us during the festival is awesome! Everyone loves it, so we put it up on the wall!","quest_name":"True Colors","quest_id":311000000},{"text":"We'd also like to invite you to our station, so we can formally thank you in person!","quest_name":"True Colors","quest_id":311000000},{"text":"Wait, how bout' coming to the station with me today? Are you heading back to the city?","quest_name":"True Colors","quest_id":311000000},{"text":"Oh, is this not a good time?","quest_name":"True Colors","quest_id":311000000},{"text":"Investigate? About what? A new case?","quest_name":"True Colors","quest_id":311000000},{"text":"Oh, I get it! In that case, it's probably not the best time for a get-together.","quest_name":"True Colors","quest_id":311000000},{"text":"That's okay! Just tell me if you need any help!","quest_name":"True Colors","quest_id":311000000},{"text":"I'm here to support the Patrollers. There was an assault near the mine recently, and they're short on people to investigate.","quest_name":"True Colors","quest_id":311000000},{"text":"What's odd is those monsters haven't caused any more trouble since we got here. Right now, we're talking to witnesses and trying to figure out what triggered the incident.","quest_name":"True Colors","quest_id":311000000},{"text":"Don't tell me it's a Tacet Discord... Hold on, just got a message... Seems like they really are stirring up trouble again. Sorry, but I gotta go check this out!","quest_name":"True Colors","quest_id":311000000},{"text":"Hey ya! Long time no see, {PlayerName}. How’s it going?","quest_name":"A Taste of Everything","quest_id":880000011},{"text":"Well, just calling to see what you're up to. Are you free now?","quest_name":"A Taste of Everything","quest_id":880000011},{"text":"No worries at all! It’s no biggie, really. Well, not as huge as diving into those tokens, that’s for sure.","quest_name":"A Taste of Everything","quest_id":880000011},{"text":"Remember my promise? About treating you to a nice meal? Well, since I’ve got a few days off and figured you’d be around, now’s the perfect time to cash in on that promise and invite you out.","quest_name":"A Taste of Everything","quest_id":880000011},{"text":"So, what do you say? How about this Jinzhou Speedster takes you on a culinary adventure at Auntie Panhua’s Restaurant?","quest_name":"A Taste of Everything","quest_id":880000011},{"text":"The Maocai she cooks is an explosion of spice and flavor! One gulp and you’ll feel the buzz in your bones!","quest_name":"A Taste of Everything","quest_id":880000011},{"text":"You know, that’s what I like. But hey, no pressure if spicy isn’t your thing. Auntie Panhua’s a culinary genius, whipping up many treats like Poached Chicken, Rising Loong... you name it! It’s all authentic Jinzhou cuisine!","quest_name":"A Taste of Everything","quest_id":880000011},{"text":"Didn’t expect you to be a foodie too. Next time I’m on patrol and find something tasty, I’ll make sure you get a taste.","quest_name":"A Taste of Everything","quest_id":880000011},{"text":"So, we’re on for a date, right?","quest_name":"A Taste of Everything","quest_id":880000011},{"text":"Let’s meet at Panhua’s Restaurant on Gourmet Street. Time-wise, just let me know before you’re ready.","quest_name":"A Taste of Everything","quest_id":880000011},{"text":"I’ll be eagerly waiting to hear from you!","quest_name":"A Taste of Everything","quest_id":880000011},{"text":"Hey there, Rover! Finally found you! Hope I didn’t keep you waiting!","quest_name":"A Taste of Everything","quest_id":880000011},{"text":"Ah, my bad! Let’s not dilly-dally any longer. Trust me, once we munch, you won’t wanna stop!","quest_name":"A Taste of Everything","quest_id":880000011},{"text":"Aw, you’re too kind, but eating always comes first! Let’s dive straight into ordering and kick-start this feast!","quest_name":"A Taste of Everything","quest_id":880000011},{"text":"No, no, no, Auntie Panhua, just forget that name! I’m begging you!","quest_name":"A Taste of Everything","quest_id":880000011},{"text":"Yeah, exactly! Meet Rover, my awesome new friend! Today’s treat’s on me, so I brought {Male=him;Female=her} here to experience your culinary magic.","quest_name":"A Taste of Everything","quest_id":880000011},{"text":"Hmm... The Candied Caltrops is fresh with just the right sweetness; the Poached Chicken sauce is Auntie Panhua’s original, unmatched anywhere else. Oh, and the Jinzhou Stew! It’s something you can only find here. I bet you’ve never tasted anything like it! Trust me, you don’t wanna miss out on this!","quest_name":"A Taste of Everything","quest_id":880000011},{"text":"I’ve decided. Let’s get all of them.","quest_name":"A Taste of Everything","quest_id":880000011},{"text":"We Patrollers don’t get paid a lot, but I love treating my friend to a feast once in a while. It’s just one meal, I won’t go broke!","quest_name":"A Taste of Everything","quest_id":880000011},{"text":"To cater to all appetites, Auntie Panhua’s rolled out a small portion menu. Same fantastic flavors, just less food waste. So, no need to fret about over-ordering!","quest_name":"A Taste of Everything","quest_id":880000011},{"text":"Rover, you enjoying the meal?","quest_name":"A Taste of Everything","quest_id":880000011},{"text":"You got it! Next time, we’ll bring Yangyang and Baizhi along. Food’s always better with more pals, right? But what should we get then?","quest_name":"A Taste of Everything","quest_id":880000011},{"text":"That’s all? Seriously? Not even Auntie Panhua’s culinary magic can shake you?","quest_name":"A Taste of Everything","quest_id":880000011},{"text":"Something special? Hmm, give me some time to think.","quest_name":"A Taste of Everything","quest_id":880000011},{"text":"Essence Medley Soup? What’s that?","quest_name":"A Taste of Everything","quest_id":880000011},{"text":"Even though I just polished off my plate, there’s always room for soup in my second stomach. Rover, fancy trying it out? Auntie Panhua, can you whip it up for us?","quest_name":"A Taste of Everything","quest_id":880000011},{"text":"Whoa, did you hear that? Brewed from the finest Jinzhou ingredients! My taste buds are tingling already... Rover, fancy trying it out? Auntie Panhua, can you whip it up for us?","quest_name":"A Taste of Everything","quest_id":880000011},{"text":"Speaking of peculiar ingredients, it does remind me of someone...","quest_name":"A Taste of Everything","quest_id":880000011},{"text":"Well… it’s Uncle Mahe!","quest_name":"A Taste of Everything","quest_id":880000011},{"text":"Auntie Panhua! You’ve got the sweetest heart. I always knew it!","quest_name":"A Taste of Everything","quest_id":880000011},{"text":"Yeah... Hold up! Rover, what’s that supposed to mean? Obviously, I...","quest_name":"A Taste of Everything","quest_id":880000011},{"text":"Seriously, don’t you have work to do? Who keeps tabs on this stuff anyway!","quest_name":"A Taste of Everything","quest_id":880000011},{"text":"Alright, let’s cut to the chase. {PlayerName} and I are here to get you to check out this recipe Auntie Panhua handed us.","quest_name":"A Taste of Everything","quest_id":880000011},{"text":"Really? C’mon, wrack your brain for it! Uncle Mahe thinks it’s more of a medicinal cuisine than a regular dish.","quest_name":"A Taste of Everything","quest_id":880000011},{"text":"Are you for real right now? My reputation as the Jinzhou Speedster is...","quest_name":"A Taste of Everything","quest_id":880000011},{"text":"I-I had no other choice! How can I remember all those safety rules when there are bad guys coming at me? They’d only slow me down... Okay, okay, next time, I’ll watch out!","quest_name":"A Taste of Everything","quest_id":880000011},{"text":"Just let Auntie Panhua know. It should be cool for you to join in!","quest_name":"A Taste of Everything","quest_id":880000011},{"text":"But there's still one last piece of the puzzle to crack: the golden-handled spoon. If we whip up the soup without figuring out what that is about, the flavor might not hit the mark, right?","quest_name":"A Taste of Everything","quest_id":880000011},{"text":"Seriously? No way! Who’d have guessed that!","quest_name":"A Taste of Everything","quest_id":880000011},{"text":"Oops, looks like I gotta step down from my role as the Jinzhou encyclopedia. I’ve never even heard of that pyrite spoon!","quest_name":"A Taste of Everything","quest_id":880000011},{"text":"We’ve covered more ground from Gourmet Street to here. Bet you haven’t had many city strolls like this before, huh?","quest_name":"A Taste of Everything","quest_id":880000011},{"text":"Even though it’s a bit of a trek, I’m thrilled to show you around my hometown. We’re nearing the Main Street, where things get even more interesting.","quest_name":"A Taste of Everything","quest_id":880000011},{"text":"...Aw, please don’t call me Xiaofang! It’s Chixia!","quest_name":"A Taste of Everything","quest_id":880000011},{"text":"Oh no, I'm doomed. It seems everyone knows my other name now.","quest_name":"A Taste of Everything","quest_id":880000011},{"text":"Cool, cool. Let’s get to business then.","quest_name":"A Taste of Everything","quest_id":880000011},{"text":"{PlayerName}, you too?! No, please no... Let’s keep that name between us, alright?","quest_name":"A Taste of Everything","quest_id":880000011},{"text":"Anyway, we're here to help Auntie Panhua recreate the Essence Medley Soup.","quest_name":"A Taste of Everything","quest_id":880000011},{"text":"The recipe says we need to stir it with a golden-handled spoon once it starts bubbling. And Koko mentioned you happen to have a pyrite spoon with that exact name, right?","quest_name":"A Taste of Everything","quest_id":880000011},{"text":"No wonder Auntie Panhua said it’s passed down through word of mouth, sparking debates over its flavor.","quest_name":"A Taste of Everything","quest_id":880000011},{"text":"Seems like this recipe is more of a shopping list than a detailed guide.","quest_name":"A Taste of Everything","quest_id":880000011},{"text":"Absolutely! Every household pulled out their secret stash of ingredients to brew up this soup. It’s gotta be divine.","quest_name":"A Taste of Everything","quest_id":880000011},{"text":"Even if it doesn’t require any fancy cooking techniques, those good reviews can’t be bogus, right? Just like Auntie Panhua said, it’s brewed from the finest Jinzhou ingredients...","quest_name":"A Taste of Everything","quest_id":880000011},{"text":"Now I’m even more eager to get a taste, knowing the backstory! Uncle Wei, mind lending us your big pyrite spoon?","quest_name":"A Taste of Everything","quest_id":880000011},{"text":"That makes sense... By the way, doesn’t Auntie Panhua already have one on standby?","quest_name":"A Taste of Everything","quest_id":880000011},{"text":"Since we’re here, might as well make the most of it. Can you lend a hand and check out my friend’s weapon?","quest_name":"A Taste of Everything","quest_id":880000011},{"text":"Check it out. That’s Uncle Wei’s weapon shop right over there.","quest_name":"A Taste of Everything","quest_id":880000011},{"text":"He’s the top-notch weapon maker in Jinzhou! If you have any weapon-related questions, just go ask him.","quest_name":"A Taste of Everything","quest_id":880000011},{"text":"How’s your weapon maintenance? Once we figure out what that big spoon deal is, you can ask him to check it for you!","quest_name":"A Taste of Everything","quest_id":880000011},{"text":"And here we are. This is the <color=Highlight>Synthesizer</color> Uncle Wei mentioned.","quest_name":"A Taste of Everything","quest_id":880000011},{"text":"Aside from crafting materials and beefing up their quality, you can also whip up some basic potions here. It’s like a one-stop shop for all your needs, whether you’re kicking it in the city or out on an adventure.","quest_name":"A Taste of Everything","quest_id":880000011},{"text":"I’ve got some synthesis materials right here. Go ahead, give it a try.","quest_name":"A Taste of Everything","quest_id":880000011},{"text":"It might seem a bit tricky just hearing about it, but once you try it hands-on, you’ll get the hang of it real quick.","quest_name":"A Taste of Everything","quest_id":880000011},{"text":"Wow, can you believe we’ve covered almost half of Jinzhou in just one day?","quest_name":"A Taste of Everything","quest_id":880000011},{"text":"Tiring, but so worth it! I’m usually tied up with patrols, so catching up with so many friends all at once like this is a total first for me.","quest_name":"A Taste of Everything","quest_id":880000011},{"text":"Introducing you to everyone, shooting the breeze... It’s like reconnecting with old friends all over again. Wait, didn’t I promise to treat you to a meal? How did it end up with you being my tour buddy instead?","quest_name":"A Taste of Everything","quest_id":880000011},{"text":"But hey, thanks to you, I finally get why folks rave about the Essence Medley Soup as they do.","quest_name":"A Taste of Everything","quest_id":880000011},{"text":"Brewed from the finest Jinzhou ingredients, with every essence distilled into a single bowl... The real treasure lies in everyone’s willingness to share their most prized grub, don’t you think?","quest_name":"A Taste of Everything","quest_id":880000011},{"text":"Exactly! If we were back in wartime, Auntie Panhua reminding me to eat on time, Uncle Mahe caring about my work, Koko fretting over my safety, Uncle Wei dropping knowledge bombs on me, and all the other folks in Jinzhou...","quest_name":"A Taste of Everything","quest_id":880000011},{"text":"They’d all without a doubt open up their pantries and share their most cherished grub with us.","quest_name":"A Taste of Everything","quest_id":880000011},{"text":"As for me, I wanna be someone who can protect every single soul in Jinzhou... including you! I wanna keep you safe too! I’ve had a great time hanging out with you.","quest_name":"A Taste of Everything","quest_id":880000011},{"text":"So, while we’re in Jinzhou, let me shoulder your worries and troubles, alright?","quest_name":"A Taste of Everything","quest_id":880000011},{"text":"You can bet on this Jinzhou Speedster’s determination!","quest_name":"A Taste of Everything","quest_id":880000011},{"text":"Yeah, no way Baizhi talks like that. She's more of a data dump kind of person. \"Super duper cool\"? Nah, too extra for her.","quest_name":"A New Companion","quest_id":880000013},{"text":"Seems like you're trying to boost your ego a bit!","quest_name":"A New Companion","quest_id":880000013},{"text":"Yeah, makes sense! Now we just gotta figure out where it came from. Who knows, we may find other cool Echoes in that place!","quest_name":"A New Companion","quest_id":880000013},{"text":"Well, both General Jiyan and Baizhi have confirmed it. No way they're lying.","quest_name":"A New Companion","quest_id":880000013},{"text":"I'll admit, the thought of someone else having an Echo inside them sounds pretty crazy to me. But with you, anything's possible.","quest_name":"A New Companion","quest_id":880000013},{"text":"You can absorb Reverberations with just your hands, like the legend says. So maybe one day you just stumbled upon this little thing and soaked it up like a sponge. Sounds feasible, I guess?","quest_name":"A New Companion","quest_id":880000013},{"text":"Sooo...","quest_name":"A New Companion","quest_id":880000013},{"text":"Do you know where exactly {Male=he;Female=she} absorbed you?","quest_name":"A New Companion","quest_id":880000013},{"text":"Yeah. It happened before {Male=he;Female=she} lost all memories, so we have to ask you.","quest_name":"A New Companion","quest_id":880000013},{"text":"Sleeping? Seriously? It's been so long! All those happenings, all that fighting, and you didn't hear anything? Well that's... Your sleeping quality is really something.","quest_name":"A New Companion","quest_id":880000013},{"text":"Hmm, I thought you'd be really different from the usual ones we see. Turns out you share a lot in common.","quest_name":"A New Companion","quest_id":880000013},{"text":"So you probably don't know your denomination, or a nick name? No wonder everyone's been calling you the \"little one\"...","quest_name":"A New Companion","quest_id":880000013},{"text":"A name? Now?","quest_name":"A New Companion","quest_id":880000013},{"text":"That's true.","quest_name":"A New Companion","quest_id":880000013},{"text":"Let's see... You want a cool one... What about \"Echo the Invincible\"? What do you say?","quest_name":"A New Companion","quest_id":880000013},{"text":"Hey, it makes every difference in the world! \"I am Echo the Invincible!\" That's what a Hero Play character would say as their transformation call!","quest_name":"A New Companion","quest_id":880000013},{"text":"Or maybe... Since you can fly and you've got those long ears... why don’t you call yourself... \"Righteous Raptor\"? Or \"Valor Hawk\"? \"Flying Fury\"?","quest_name":"A New Companion","quest_id":880000013},{"text":"Why? I love it when people call me the Jinzhou Speedster. Doesn't that sound awesome?","quest_name":"A New Companion","quest_id":880000013},{"text":"What's wrong? What are you muttering about? Abra... what? Sounds like you're reading a spell.","quest_name":"A New Companion","quest_id":880000013},{"text":"Sure, we won't. Got it.","quest_name":"A New Companion","quest_id":880000013},{"text":"Well, that didn't work out. I was hoping we could get some answers from the little... I mean, from Abby, but now we're back at square one.","quest_name":"A New Companion","quest_id":880000013},{"text":"I really thought we could figure out where Abby came from. It might not lead us to other special Echoes, but it's at least a starting point to uncover {PlayerName}'s past. Then we'll have something to do before asking Madam Magistrate and our Sentinel about it again.","quest_name":"A New Companion","quest_id":880000013},{"text":"Why do you sound so unsure? Didn't you see it all with your own eyes?","quest_name":"A New Companion","quest_id":880000013},{"text":"Hmm… Abby, can you show us again? I'm super curious how you did that. Who knows, we might learn something.","quest_name":"A New Companion","quest_id":880000013},{"text":"Uh... What? Did something happen?","quest_name":"A New Companion","quest_id":880000013},{"text":"So... you didn't really do anything?","quest_name":"A New Companion","quest_id":880000013},{"text":"Yeah, it looks that way. You can't even hold your shape for very long yet...","quest_name":"A New Companion","quest_id":880000013},{"text":"You're so real for that, Abby.","quest_name":"A New Companion","quest_id":880000013},{"text":"Knew it. Nothing about {PlayerName}'s ever gonna be easy to figure out... Hmm. Maybe we should bring Baizhi, Mr. Xiangli Yao, and all the researchers in Jinzhou... No, in the entire Huanglong together. They'll do a nice and thorough examination on Abby, and then...","quest_name":"A New Companion","quest_id":880000013},{"text":"Our Sentinel protects every one of us. Of course it's cool!","quest_name":"A New Companion","quest_id":880000013},{"text":"But... why are you talking about food again. Didn't you just stuff your face? What? Is your stomach a black hole?","quest_name":"A New Companion","quest_id":880000013},{"text":"Oh, Yangyang! What's there to be shy about? If you want to see {PlayerName}, just tell {Male=him;Female=her}!","quest_name":"Moonlit Reunion","quest_id":880000015},{"text":"So, what have you been up to these past few days? Feelin' lonely without us around?","quest_name":"Moonlit Reunion","quest_id":880000015},{"text":"Wanna go see some fireworks? How about some Moon Shooting? With the festival just around the corner, there's a really cool spot we can take you to.","quest_name":"Moonlit Reunion","quest_id":880000015},{"text":"Yep, I caught them hanging lanterns all around City Hall. Every street and alley is gonna be glowing, I can't wait to see it all lit up!","quest_name":"Moonlit Reunion","quest_id":880000015},{"text":"And we’ve got special Jinzhou traditions you won’t find anywhere else.","quest_name":"Moonlit Reunion","quest_id":880000015},{"text":"Like Taoyuan Vale! Folks go there a few days before the festival to write their wishes onto paper, then hang them on branches or toss 'em into Moontree Lodge.","quest_name":"Moonlit Reunion","quest_id":880000015},{"text":"They say wishes made during these days are sure to come true. Works like a charm.","quest_name":"Moonlit Reunion","quest_id":880000015},{"text":"Wanna give it a go, {PlayerName}? All you gotta do is write down your wish, real simple! Yangyang, Baizhi and I are already here.","quest_name":"Moonlit Reunion","quest_id":880000015},{"text":"Great!","quest_name":"Moonlit Reunion","quest_id":880000015},{"text":"See you at Taoyuan Vale.","quest_name":"Moonlit Reunion","quest_id":880000015}]}