{"words":[{"word":"paintings","count":14},{"word":"i'll","count":9},{"word":"truth","count":9},{"word":"painting","count":9},{"word":"mingyan's","count":8},{"word":"art","count":8},{"word":"mr","count":8},{"word":"playername","count":7},{"word":"artist","count":7},{"word":"mingyan","count":7},{"word":"really","count":6},{"word":"details","count":6},{"word":"behind","count":6},{"word":"arcane","count":6},{"word":"original","count":6},{"word":"pigments","count":6},{"word":"paw","count":5},{"word":"studio","count":5},{"word":"many","count":5},{"word":"never","count":5},{"word":"case","count":5},{"word":"sorry","count":5},{"word":"tale","count":5},{"word":"into","count":5},{"word":"yes","count":5},{"word":"something","count":5},{"word":"baici","count":5},{"word":"someone","count":4},{"word":"shanyun","count":4},{"word":"exchange","count":4},{"word":"i've","count":4},{"word":"uh","count":4},{"word":"thank","count":4},{"word":"people","count":4},{"word":"making","count":4},{"word":"trouble","count":4},{"word":"decided","count":4},{"word":"thought","count":4},{"word":"brought","count":4},{"word":"made","count":4},{"word":"hmm","count":3},{"word":"take","count":3},{"word":"maybe","count":3},{"word":"um","count":3},{"word":"finished","count":3},{"word":"give","count":3},{"word":"madam","count":3},{"word":"juyao","count":3},{"word":"evidence","count":3},{"word":"camp","count":3},{"word":"patroller","count":3},{"word":"said","count":3},{"word":"things","count":3},{"word":"help","count":3},{"word":"time","count":3},{"word":"real","count":3},{"word":"first","count":3},{"word":"years","count":3},{"word":"felt","count":3},{"word":"past","count":3},{"word":"mine","count":3},{"word":"investigation","count":3},{"word":"statement","count":3},{"word":"ask","count":3},{"word":"around","count":3},{"word":"ink","count":3},{"word":"must","count":3},{"word":"involved","count":3},{"word":"record","count":3},{"word":"mentioned","count":3},{"word":"everything","count":3},{"word":"others","count":3},{"word":"artists","count":3},{"word":"used","count":3},{"word":"use","count":3},{"word":"hurt","count":3},{"word":"learned","count":3},{"word":"chixia","count":3},{"word":"expect","count":2},{"word":"hearing","count":2},{"word":"s-should","count":2},{"word":"little","count":2},{"word":"raise","count":2},{"word":"left","count":2},{"word":"testify","count":2},{"word":"okay","count":2},{"word":"else","count":2},{"word":"huh","count":2},{"word":"actually","count":2},{"word":"nice","count":2},{"word":"coming","count":2},{"word":"forgeries","count":2},{"word":"thing","count":2},{"word":"kind","count":2},{"word":"already","count":2},{"word":"any","count":2},{"word":"talking","count":2},{"word":"uncover","count":2},{"word":"situation","count":2},{"word":"find","count":2},{"word":"painted","count":2},{"word":"life","count":2},{"word":"ago","count":2},{"word":"create","count":2},{"word":"almost","count":2},{"word":"lot","count":2},{"word":"bring","count":2},{"word":"good","count":2},{"word":"major","count":2},{"word":"yet","count":2},{"word":"happened","count":2},{"word":"h-hello","count":2},{"word":"hehe","count":2},{"word":"learning","count":2},{"word":"assault","count":2},{"word":"push","count":2},{"word":"forward","count":2},{"word":"touch","count":2},{"word":"idea","count":2},{"word":"artworks","count":2},{"word":"diary","count":2},{"word":"start","count":2},{"word":"wonder","count":2},{"word":"shifty","count":2},{"word":"earlier","count":2},{"word":"yinfeng","count":2},{"word":"signature","count":2},{"word":"shilang's","count":2},{"word":"transaction","count":2},{"word":"theory","count":2},{"word":"batch","count":2},{"word":"test","count":2},{"word":"hide","count":2},{"word":"barge","count":2},{"word":"copies","count":2},{"word":"wanted","count":2},{"word":"piece","count":2},{"word":"always","count":2},{"word":"pieces","count":2},{"word":"paint","count":2},{"word":"realize","count":2},{"word":"forte","count":2},{"word":"words","count":2},{"word":"met","count":2},{"word":"hope","count":2},{"word":"true","count":2},{"word":"deep","count":2},{"word":"slow","count":2},{"word":"ore","count":2},{"word":"bumped","count":2},{"word":"investigate","count":2},{"word":"surroundings","count":2},{"word":"follow","count":2},{"word":"scene","count":2},{"word":"incident","count":2},{"word":"offense","count":2},{"word":"big","count":1},{"word":"crowd","count":1},{"word":"stand","count":1},{"word":"kitty","count":1},{"word":"ah","count":1},{"word":"show","count":1},{"word":"paws","count":1},{"word":"w-wait","count":1},{"word":"raised","count":1},{"word":"sentence","count":1},{"word":"count","count":1},{"word":"try","count":1},{"word":"handle","count":1},{"word":"everyone","count":1},{"word":"another","count":1},{"word":"shot","count":1},{"word":"y-yes","count":1},{"word":"minute","count":1},{"word":"oh","count":1},{"word":"appreciate","count":1},{"word":"handed","count":1},{"word":"gathered","count":1},{"word":"exile's","count":1},{"word":"patrollers","count":1},{"word":"deny","count":1},{"word":"fact","count":1},{"word":"producing","count":1},{"word":"trading","count":1},{"word":"fine","count":1},{"word":"helped","count":1},{"word":"huge","count":1},{"word":"relief","count":1},{"word":"face","count":1},{"word":"spectators","count":1},{"word":"watch","count":1},{"word":"nervous","count":1},{"word":"mess","count":1},{"word":"please","count":1},{"word":"remind","count":1},{"word":"helps","count":1},{"word":"probably","count":1},{"word":"eh","count":1},{"word":"b-but","count":1},{"word":"spoken","count":1},{"word":"front","count":1},{"word":"h-how","count":1},{"word":"add","count":1},{"word":"chose","count":1},{"word":"matters","count":1},{"word":"promise","count":1},{"word":"th-the","count":1},{"word":"r-rover","count":1},{"word":"scare","count":1},{"word":"f-finding","count":1},{"word":"inspiration","count":1},{"word":"night","count":1},{"word":"often","count":1},{"word":"sparks","count":1},{"word":"creativity","count":1},{"word":"course","count":1},{"word":"heard","count":1},{"word":"hoped","count":1},{"word":"lied","count":1},{"word":"drag","count":1},{"word":"anyone","count":1},{"word":"n-no","count":1},{"word":"ghost","count":1},{"word":"stories","count":1},{"word":"bringing","count":1},{"word":"creatures","count":1},{"word":"fantasies","count":1},{"word":"sounds","count":1},{"word":"fairy","count":1},{"word":"caught","count":1},{"word":"people's","count":1},{"word":"attention","count":1},{"word":"jinzhou","count":1},{"word":"story","count":1},{"word":"rounds","count":1},{"word":"dangers","count":1},{"word":"holds","count":1},{"word":"feels","count":1},{"word":"threat","count":1},{"word":"late","count":1},{"word":"step","count":1},{"word":"strayed","count":1},{"word":"artist's","count":1},{"word":"intentions","count":1},{"word":"caused","count":1},{"word":"latest","count":1},{"word":"events","count":1},{"word":"nothing","count":1},{"word":"t-that's","count":1},{"word":"stop","count":1},{"word":"prevent","count":1},{"word":"repeating","count":1},{"word":"unfortunately","count":1},{"word":"investigating","count":1},{"word":"found","count":1},{"word":"clues","count":1},{"word":"hoping","count":1},{"word":"meet","count":1},{"word":"old","count":1},{"word":"acquaintance","count":1},{"word":"knows","count":1},{"word":"o-ok","count":1},{"word":"glad","count":1},{"word":"investig","count":1},{"word":"o-okay","count":1},{"word":"happen","count":1},{"word":"er","count":1},{"word":"w-we","count":1},{"word":"lively","count":1},{"word":"bright","count":1},{"word":"freedom","count":1},{"word":"joy","count":1},{"word":"interrupt","count":1},{"word":"mind","count":1},{"word":"normally","count":1},{"word":"living","count":1},{"word":"neither","count":1},{"word":"exiles","count":1},{"word":"told","count":1},{"word":"noticed","count":1},{"word":"exiles'","count":1},{"word":"hands","count":1},{"word":"blackened","count":1},{"word":"suddenly","count":1},{"word":"hit","count":1},{"word":"constant","count":1},{"word":"exposure","count":1},{"word":"sticks","count":1},{"word":"showed","count":1},{"word":"match","count":1},{"word":"described","count":1},{"word":"shows","count":1},{"word":"mood","count":1},{"word":"swings","count":1},{"word":"affected","count":1},{"word":"strange","count":1},{"word":"started","count":1},{"word":"happening","count":1},{"word":"makes","count":1},{"word":"sense","count":1},{"word":"changing","count":1},{"word":"subject","count":1},{"word":"b-before","count":1},{"word":"proceed","count":1},{"word":"wish","count":1},{"word":"present","count":1},{"word":"audio","count":1},{"word":"recording","count":1},{"word":"court","count":1},{"word":"initially","count":1},{"word":"changed","count":1},{"word":"stepped","count":1},{"word":"trickery","count":1},{"word":"misinformation","count":1},{"word":"later","count":1},{"word":"threats","count":1},{"word":"led","count":1},{"word":"path","count":1},{"word":"forging","count":1},{"word":"understand","count":1},{"word":"heart","count":1},{"word":"wavered","count":1},{"word":"none","count":1},{"word":"would've","count":1},{"word":"turning","count":1},{"word":"quit","count":1},{"word":"saying","count":1},{"word":"mastermind","count":1},{"word":"fair","count":1},{"word":"recognize","count":1},{"word":"difference","count":1},{"word":"however","count":1},{"word":"judging","count":1},{"word":"seems","count":1},{"word":"ability","count":1},{"word":"stabilized","count":1},{"word":"successfully","count":1},{"word":"except","count":1},{"word":"seeking","count":1},{"word":"perfection","count":1},{"word":"choose","count":1},{"word":"highest","count":1},{"word":"quality","count":1},{"word":"important","count":1},{"word":"accidentally","count":1},{"word":"discovered","count":1},{"word":"interesting","count":1},{"word":"materials","count":1},{"word":"purer","count":1},{"word":"brighter","count":1},{"word":"able","count":1},{"word":"blend","count":1},{"word":"naturally","count":1},{"word":"retain","count":1},{"word":"color","count":1},{"word":"longer","count":1},{"word":"contrast","count":1},{"word":"mineral","count":1},{"word":"scraps","count":1},{"word":"hold","count":1},{"word":"smudging","count":1},{"word":"slightest","count":1},{"word":"distinguish","count":1},{"word":"fakes","count":1},{"word":"simply","count":1},{"word":"analyzing","count":1},{"word":"creator","count":1},{"word":"serenity","count":1},{"word":"xiehua","count":1},{"word":"village","count":1},{"word":"hear","count":1},{"word":"ok","count":1},{"word":"terminal","count":1},{"word":"prove","count":1},{"word":"request","count":1},{"word":"permission","count":1},{"word":"experience","count":1},{"word":"truly","count":1},{"word":"resonates","count":1},{"word":"accept","count":1},{"word":"drew","count":1},{"word":"heartfelt","count":1},{"word":"creations","count":1},{"word":"formed","count":1},{"word":"shaped","count":1},{"word":"today","count":1},{"word":"proving","count":1},{"word":"single","count":1},{"word":"cause","count":1},{"word":"responsibility","count":1},{"word":"heartbroken","count":1},{"word":"believed","count":1},{"word":"sealing","count":1},{"word":"expected","count":1},{"word":"continue","count":1},{"word":"causing","count":1},{"word":"harm","count":1},{"word":"'s","count":1},{"word":"rather","count":1},{"word":"sought","count":1},{"word":"run","count":1},{"word":"highly","count":1},{"word":"esteemed","count":1},{"word":"calligraphy","count":1},{"word":"institution","count":1},{"word":"suppressed","count":1},{"word":"creative","count":1},{"word":"spirit","count":1},{"word":"violated","count":1},{"word":"artists'","count":1},{"word":"dignity","count":1},{"word":"sake","count":1},{"word":"wealth","count":1},{"word":"cherished","count":1},{"word":"become","count":1},{"word":"tool","count":1},{"word":"profit","count":1},{"word":"works","count":1},{"word":"held","count":1},{"word":"dear","count":1},{"word":"tools","count":1},{"word":"gain","count":1},{"word":"insulting","count":1},{"word":"imitators","count":1},{"word":"set","count":1},{"word":"completed","count":1},{"word":"light","count":1},{"word":"injuries","count":1},{"word":"gift","count":1},{"word":"gave","count":1},{"word":"inferior","count":1},{"word":"approve","count":1},{"word":"value","count":1},{"word":"matter","count":1},{"word":"self","count":1},{"word":"whoever","count":1},{"word":"safe","count":1},{"word":"times","count":1},{"word":"passionate","count":1},{"word":"discussing","count":1},{"word":"fire","count":1},{"word":"inside","count":1},{"word":"fade","count":1},{"word":"away","count":1},{"word":"discussions","count":1},{"word":"duels","count":1},{"word":"friendship","count":1},{"word":"seeing","count":1},{"word":"pain","count":1},{"word":"lose","count":1},{"word":"loves","count":1},{"word":"disappear","count":1},{"word":"honest","count":1},{"word":"correct","count":1},{"word":"mistakes","count":1},{"word":"friend","count":1},{"word":"helping","count":1},{"word":"seem","count":1},{"word":"pretty","count":1},{"word":"news","count":1},{"word":"given","count":1},{"word":"courage","count":1},{"word":"joke","count":1},{"word":"trolley","count":1},{"word":"worn","count":1},{"word":"carried","count":1},{"word":"heavy","count":1},{"word":"transported","count":1},{"word":"moved","count":1},{"word":"elsewhere","count":1},{"word":"buyers","count":1},{"word":"shilang","count":1},{"word":"ones","count":1},{"word":"stole","count":1},{"word":"phew","count":1},{"word":"thanks","count":1},{"word":"wait","count":1},{"word":"trying","count":1},{"word":"clearer","count":1},{"word":"explain","count":1},{"word":"close","count":1},{"word":"sure","count":1},{"word":"respond","count":1},{"word":"friendly","count":1},{"word":"rude","count":1},{"word":"turn","count":1},{"word":"best","count":1},{"word":"express","count":1},{"word":"feelings","count":1},{"word":"properly","count":1},{"word":"next","count":1}],"lines":[{"text":"I didn't expect such a big crowd at the hearing...","quest_name":"True Colors","quest_id":311000000},{"text":"Hmm... S-should I take the stand myself? What do you think, little kitty?","quest_name":"True Colors","quest_id":311000000},{"text":"Ah, maybe we can do a little show of... um... paws. Raise your left paw if you think I should testify, or your right paw if...","quest_name":"True Colors","quest_id":311000000},{"text":"W-wait! You raised your left paw before I even finished my sentence... No, that doesn't count. Let's try again.","quest_name":"True Colors","quest_id":311000000},{"text":"Okay, if you raise your right paw, I'll... let someone else handle it.","quest_name":"True Colors","quest_id":311000000},{"text":"Hmm... right paw, huh? Well... I did actually want to tell everyone the truth myself. Let's give this another shot.","quest_name":"True Colors","quest_id":311000000},{"text":"Now? Y-yes, Madam Juyao! I... I'll be there in a minute!","quest_name":"True Colors","quest_id":311000000},{"text":"{PlayerName}, oh, you're here! It's... it's really nice to see you! And... I appreciate you coming.","quest_name":"True Colors","quest_id":311000000},{"text":"I just handed over all the evidence we gathered from Mingyan's studio and the Exile's camp to the Patrollers.","quest_name":"True Colors","quest_id":311000000},{"text":"Now the Shanyun Art Exchange can't deny the fact they were producing and trading art forgeries.","quest_name":"True Colors","quest_id":311000000},{"text":"But... there is one more thing. The Patroller said we still need someone to testify in the hearing.","quest_name":"True Colors","quest_id":311000000},{"text":"You're really kind, but... um, I'll be fine to do this myself. You've already helped me so much, even just having you here is a huge relief.","quest_name":"True Colors","quest_id":311000000},{"text":"Some things, I've got to face on my own.","quest_name":"True Colors","quest_id":311000000},{"text":"That said... I, uh, didn't... didn't expect there would be so many spectators coming to watch...","quest_name":"True Colors","quest_id":311000000},{"text":"If I get nervous and mess up any details, could you please help to remind me?","quest_name":"True Colors","quest_id":311000000},{"text":"Thank you! Having you here helps, more than you know.","quest_name":"True Colors","quest_id":311000000},{"text":"It's about time. We should probably go in, huh?","quest_name":"True Colors","quest_id":311000000},{"text":"Eh? B-but... I've... I've never spoken in front of so many people before...","quest_name":"True Colors","quest_id":311000000},{"text":"H-how about... you do the talking, and, um, I'll add details... if, if I have to?","quest_name":"True Colors","quest_id":311000000},{"text":"You're right... Then... I'll... I'll do it myself...","quest_name":"True Colors","quest_id":311000000},{"text":"...You're right.","quest_name":"True Colors","quest_id":311000000},{"text":"I was the one who chose to uncover the truth behind this case. I can't back down now, not when it matters most.","quest_name":"True Colors","quest_id":311000000},{"text":"I'll give it my all, I promise. Let's go.","quest_name":"True Colors","quest_id":311000000},{"text":"Madam Juyao, th-the situation is...","quest_name":"True Colors","quest_id":311000000},{"text":"...","quest_name":"True Colors","quest_id":311000000},{"text":"I...","quest_name":"True Colors","quest_id":311000000},{"text":"...","quest_name":"True Colors","quest_id":311000000},{"text":"R-rover? You're here...","quest_name":"True Colors","quest_id":311000000},{"text":"Sorry, did I scare you just now?","quest_name":"True Colors","quest_id":311000000},{"text":"...F-finding inspiration.","quest_name":"True Colors","quest_id":311000000},{"text":"The night... often sparks my creativity...","quest_name":"True Colors","quest_id":311000000},{"text":"Of course not!","quest_name":"True Colors","quest_id":311000000},{"text":"I... I heard about the tale of the Arcane Artist and hoped to find out who they are...","quest_name":"True Colors","quest_id":311000000},{"text":"Sorry I lied to you, I just... didn't want to drag anyone else into this...","quest_name":"True Colors","quest_id":311000000},{"text":"N-no, I'm not into ghost stories.","quest_name":"True Colors","quest_id":311000000},{"text":"Bringing painted creatures to life, making fantasies real—it sounds like a fairy tale, but when the Arcane Artist first caught people's attention in Jinzhou years ago, it was more than just a tale.","quest_name":"True Colors","quest_id":311000000},{"text":"Now this story is making the rounds again. Most don't see the dangers it holds. As someone who feels the threat, I... I want to uncover the truth before it's too late.","quest_name":"True Colors","quest_id":311000000},{"text":"Yes, there was once an artist who could create paintings that felt so real, you could almost step into them...","quest_name":"True Colors","quest_id":311000000},{"text":"But these paintings, they strayed from the artist's original intentions and... caused a lot of trouble.","quest_name":"True Colors","quest_id":311000000},{"text":"I don't know who's behind these latest events, but if it's really the Arcane Artist... their paintings will bring nothing but trouble. T-that's why I... I have to stop them, to prevent the past from repeating itself...","quest_name":"True Colors","quest_id":311000000},{"text":"Unfortunately, I'm... not very good at investigating, so I haven't found any major clues yet.","quest_name":"True Colors","quest_id":311000000},{"text":"I'm here for the Arcane Artist, but also hoping to meet an old acquaintance. Maybe he knows what happened in the mine...","quest_name":"True Colors","quest_id":311000000},{"text":"Is that so? O-ok.","quest_name":"True Colors","quest_id":311000000},{"text":"If this is the situation...","quest_name":"True Colors","quest_id":311000000},{"text":"H-hello... No, it's not... uh... no, thank you...","quest_name":"True Colors","quest_id":311000000},{"text":"Really? Hehe, I'm glad you all like it...","quest_name":"True Colors","quest_id":311000000},{"text":"Uh... but we're still investig— I... O-okay.","quest_name":"True Colors","quest_id":311000000},{"text":"Sorry...","quest_name":"True Colors","quest_id":311000000},{"text":"Did something just happen over there...","quest_name":"True Colors","quest_id":311000000},{"text":"S-should we go as well?","quest_name":"True Colors","quest_id":311000000},{"text":"You could be right, but there's one other thing...","quest_name":"True Colors","quest_id":311000000},{"text":"After learning about the details of the assault, we decided to push forward with the investigation to get to the truth.","quest_name":"True Colors","quest_id":311000000},{"text":"I haven't finished my statement, Mr. Baici!","quest_name":"True Colors","quest_id":311000000},{"text":"Er, h-hello... we are...","quest_name":"True Colors","quest_id":311000000},{"text":"She... she wasn't in her studio, so we thought we could ask around.","quest_name":"True Colors","quest_id":311000000},{"text":"W-we are actually here for Mingyan's paintings. She wasn't in her studio, so we thought we could ask around.","quest_name":"True Colors","quest_id":311000000},{"text":"I kind of like it, myself. It's lively, bright... Almost like you can touch the freedom and joy she felt painting it.","quest_name":"True Colors","quest_id":311000000},{"text":"Sorry to interrupt, but mind if I ask what you normally do for a living?","quest_name":"True Colors","quest_id":311000000},{"text":"I have an idea.","quest_name":"True Colors","quest_id":311000000},{"text":"Yes. I think... neither these Exiles nor Mingyan has told the truth.","quest_name":"True Colors","quest_id":311000000},{"text":"I noticed some of the Exiles' hands were blackened... The thought suddenly hit me, what if it's from constant exposure to ink?","quest_name":"True Colors","quest_id":311000000},{"text":"If so, they must be making a lot of pigments and ink sticks...","quest_name":"True Colors","quest_id":311000000},{"text":"The painting they showed us and the artworks in the studio... they all match what Mingyan described in her diary.","quest_name":"True Colors","quest_id":311000000},{"text":"Her diary shows us she had major mood swings, which really affected her art.","quest_name":"True Colors","quest_id":311000000},{"text":"All these strange things... started happening after the Shanyun Art Exchange got involved.","quest_name":"True Colors","quest_id":311000000},{"text":"Good idea.","quest_name":"True Colors","quest_id":311000000},{"text":"Makes sense.","quest_name":"True Colors","quest_id":311000000},{"text":"So the Shanyun Art Exchange has been involved in Mingyan's case right from the start.","quest_name":"True Colors","quest_id":311000000},{"text":"No wonder they got all shifty when we brought up Mingyan earlier...","quest_name":"True Colors","quest_id":311000000},{"text":"Yinfeng... Yes...","quest_name":"True Colors","quest_id":311000000},{"text":"It was his signature on Mr. Shilang's transaction record.","quest_name":"True Colors","quest_id":311000000},{"text":"I have a theory... but we need that \"batch of paintings\" they mentioned to test it...","quest_name":"True Colors","quest_id":311000000},{"text":"But there are so many more people in the camp now! How will we get in?","quest_name":"True Colors","quest_id":311000000},{"text":"They might hide all the evidence if we barge in like that...","quest_name":"True Colors","quest_id":311000000},{"text":"No... Mr. Baici, you're changing the subject.","quest_name":"True Colors","quest_id":311000000},{"text":"B-Before we proceed, I wish to present this audio recording to the court.","quest_name":"True Colors","quest_id":311000000},{"text":"Mingyan was initially only making copies. Everything changed after you stepped in.","quest_name":"True Colors","quest_id":311000000},{"text":"Trickery, misinformation, and later on even threats... She was led down the path of forging artworks for you.","quest_name":"True Colors","quest_id":311000000},{"text":"I do understand that... if her own heart hadn't wavered, none of this would've happened... But there was already no turning back by the time she wanted to quit.","quest_name":"True Colors","quest_id":311000000},{"text":"So, saying she was the mastermind behind it all... that's just not fair.","quest_name":"True Colors","quest_id":311000000},{"text":"...Mr. Baici, do you recognize this painting?","quest_name":"True Colors","quest_id":311000000},{"text":"Then can you tell the difference between this one and the others?","quest_name":"True Colors","quest_id":311000000},{"text":"However, judging from these paintings, it seems Mingyan's ability never stabilized successfully, except for this original piece.","quest_name":"True Colors","quest_id":311000000},{"text":"Artists seeking perfection always choose the highest quality pigments for their most important pieces.","quest_name":"True Colors","quest_id":311000000},{"text":"During our investigation of the studio, I accidentally got paint on me and discovered something interesting about the materials used in these paintings.","quest_name":"True Colors","quest_id":311000000},{"text":"The original paintings had pigments that were purer and brighter, able to blend more naturally and retain color for longer.","quest_name":"True Colors","quest_id":311000000},{"text":"In contrast, the forgeries used pigments made from mineral scraps. These don't hold up the same, smudging at the slightest touch.","quest_name":"True Colors","quest_id":311000000},{"text":"We can distinguish the real paintings from the fakes simply by analyzing the ink used.","quest_name":"True Colors","quest_id":311000000},{"text":"...","quest_name":"True Colors","quest_id":311000000},{"text":"Because the original creator of \"Serenity in Xiehua Village\" is me.","quest_name":"True Colors","quest_id":311000000},{"text":"I hear people talking.","quest_name":"True Colors","quest_id":311000000},{"text":"OK, I'll use my Terminal to record it, just in case.","quest_name":"True Colors","quest_id":311000000},{"text":"...Madam Juyao, to prove my statement, I request your permission to use and paint with one of these copies.","quest_name":"True Colors","quest_id":311000000},{"text":"Yes. Mingyan's experience has made me realize something.","quest_name":"True Colors","quest_id":311000000},{"text":"To create art that truly resonates, I must first accept myself.","quest_name":"True Colors","quest_id":311000000},{"text":"The paintings I drew in the past... they were heartfelt creations, pieces of my life. They formed my past and shaped who I am today.","quest_name":"True Colors","quest_id":311000000},{"text":"It's not just about proving a single painting... it's about so much more...","quest_name":"True Colors","quest_id":311000000},{"text":"If my Forte is the cause behind all this, then I must take responsibility... I can't just let this go on and hurt others.","quest_name":"True Colors","quest_id":311000000},{"text":"When I learned the truth, I was heartbroken...","quest_name":"True Colors","quest_id":311000000},{"text":"I believed that by sealing my Forte, no one would get hurt because of my paintings. I never expected them to continue causing harm after all these years.","quest_name":"True Colors","quest_id":311000000},{"text":"But {PlayerName}'s words made me realize something.","quest_name":"True Colors","quest_id":311000000},{"text":"It was never about the paintings themselves, but rather those who sought to use them to hurt others.","quest_name":"True Colors","quest_id":311000000},{"text":"Mr. Baici, you run a highly esteemed calligraphy and painting institution, yet you've suppressed the creative spirit and violated these artists' dignity, all for the sake of wealth.","quest_name":"True Colors","quest_id":311000000},{"text":"Everything they cherished has now become a tool for profit... The works they held dear are just tools for your gain, insulting to both the original artists and their imitators.","quest_name":"True Colors","quest_id":311000000},{"text":"Set before you is the original painting from many years ago and the one I've just completed. Now, everything has been brought to light.","quest_name":"True Colors","quest_id":311000000},{"text":"Your injuries...","quest_name":"True Colors","quest_id":311000000},{"text":"I brought you a gift...","quest_name":"True Colors","quest_id":311000000},{"text":"This is your painting.","quest_name":"True Colors","quest_id":311000000},{"text":"It's the one you gave me when we first met.","quest_name":"True Colors","quest_id":311000000},{"text":"Your paintings were never inferior to mine. Just look at this piece, even you approve of its value. It doesn't matter who painted it.","quest_name":"True Colors","quest_id":311000000},{"text":"Mingyan, I hope you can find your true self, whoever she is. I know you can do it.","quest_name":"True Colors","quest_id":311000000},{"text":"I think it's safe to say she'll give it some thought.","quest_name":"True Colors","quest_id":311000000},{"text":"During the few times we met, she was always passionate about discussing art with me. I think that fire inside her won't just fade away.","quest_name":"True Colors","quest_id":311000000},{"text":"Come to think of it, the deep discussions we had and the painting duels back then felt like true friendship.","quest_name":"True Colors","quest_id":311000000},{"text":"So... seeing her in so much pain, I just had to help.","quest_name":"True Colors","quest_id":311000000},{"text":"I don't want Mingyan to lose hope and have someone who loves painting so much just disappear...","quest_name":"True Colors","quest_id":311000000},{"text":"To be honest, I didn't just see this case through to correct mistakes or help the artists. Deep down, I...I didn't want to let you down.","quest_name":"True Colors","quest_id":311000000},{"text":"I wanted to tell you this back at the mine, but the words just didn't come out right...","quest_name":"True Colors","quest_id":311000000},{"text":"Thank you for being my friend and helping me through all of this, {PlayerName}.","quest_name":"True Colors","quest_id":311000000},{"text":"You seem to be pretty slow on the news, {PlayerName}.","quest_name":"True Colors","quest_id":311000000},{"text":"Hehe... You've given me the courage to joke around.","quest_name":"True Colors","quest_id":311000000},{"text":"Hmm... well...","quest_name":"True Colors","quest_id":311000000},{"text":"Let's take it slow for now.","quest_name":"True Colors","quest_id":311000000},{"text":"So this Shanyun Art Exchange has been involved in Mingyan's case right from the start.","quest_name":"True Colors","quest_id":311000000},{"text":"No wonder they got all shifty when we brought up Mingyan earlier...","quest_name":"True Colors","quest_id":311000000},{"text":"Yinfeng... Yes...","quest_name":"True Colors","quest_id":311000000},{"text":"It was his signature on Mr. Shilang's transaction record.","quest_name":"True Colors","quest_id":311000000},{"text":"I have a theory... but we need that \"batch of paintings\" they mentioned to test it...","quest_name":"True Colors","quest_id":311000000},{"text":"But there are so many more people in the camp now! How should we get in?","quest_name":"True Colors","quest_id":311000000},{"text":"They might hide all the evidence if we barge in like that...","quest_name":"True Colors","quest_id":311000000},{"text":"Okay.","quest_name":"True Colors","quest_id":311000000},{"text":"The trolley is worn... Maybe it carried something very heavy.","quest_name":"True Colors","quest_id":311000000},{"text":"Could it be they transported ore, made pigments from them, and then moved the pigments elsewhere?","quest_name":"True Colors","quest_id":311000000},{"text":"Could the buyers Mr. Shilang mentioned be the ones who stole the ore?","quest_name":"True Colors","quest_id":311000000},{"text":"After {PlayerName} and I bumped into each other, we decided to investigate the surroundings and follow Patroller Chixia to the scene of the incident.","quest_name":"True Colors","quest_id":311000000},{"text":"It was there we learned about the details of Mingyan's offense and the truth behind the tale of the Arcane Artist.","quest_name":"True Colors","quest_id":311000000},{"text":"After {PlayerName} and I bumped into each other, we decided to investigate the surroundings and follow Patroller Chixia to the scene of the incident.","quest_name":"True Colors","quest_id":311000000},{"text":"It was there we learned about the details of Mingyan's offense and the truth behind the tale of the Arcane Artist.","quest_name":"True Colors","quest_id":311000000},{"text":"Phew... Sorry to trouble you, {PlayerName}.","quest_name":"True Colors","quest_id":311000000},{"text":"Thanks... Uh, wait, I haven't said why.","quest_name":"True Colors","quest_id":311000000},{"text":"What I'm trying to say is...","quest_name":"True Colors","quest_id":311000000},{"text":"If I had been clearer, you wouldn't have had to explain things to Chixia for me.","quest_name":"True Colors","quest_id":311000000},{"text":"She's really nice. It's just... we're not that close, and I'm not sure how to respond to how friendly she is... I didn't want to be rude, so I... I couldn't bring myself to turn her down.","quest_name":"True Colors","quest_id":311000000},{"text":"I'll do my best not to trouble you and express my feelings properly next time...","quest_name":"True Colors","quest_id":311000000},{"text":"Thank you...","quest_name":"True Colors","quest_id":311000000},{"text":"After learning about the details of the assault, we decided to push forward with the investigation to get to the truth.","quest_name":"True Colors","quest_id":311000000},{"text":"I haven't finished my statement, Mr. Baici!","quest_name":"True Colors","quest_id":311000000}]}